Workbook
Name _Hlk169617268: Quotes!$E$575
Name _Hlk84432143: Quotes!$E$605

Sheet Quotes
A1: Quote Num. | B1: Created By | C1: Customer | D1: Cust. Contact | E1: Description | F1: Start Date | G1: Due Date | H1: Maturity Date | I1: Quote Status | J1: In L Drive | K1: Latest Rev | L1: Column1
A2: Q06 | B2: JT | C2: RSA | D2: Jon Trembley | E2: Example Quote | F2: 44837 | G2: 44837 | H2: 44837 | I2: Not Accepted | J2: No
A3: Q07 | B3: JT | C3: Avient | D3: Aaron Johnson | E3: Line C Acrison Takeover | F3: 44837 | G3: 44841 | I3: Not Accepted | J3: No
A4: Q08 | B4: TF | C4: Upstate Batavia | D4: Oleg S. | E4: Vacuum Cups | F4: 44837 | G4: 44837 | I4: PO Received | J4: Yes
A5: Q09 | B5: JRW | C5: Cedars | E5: Scara Robot Case Packing | F5: 44838 | G5: 44838 | I5: Not Accepted | J5: No
A6: Q010 | B6: TF | C6: Iberdrola | D6: Dan Arcangeli | E6: SAP Bing, Can., Geneva | F6: 44838 | G6: 44839 | I6: PO Received | J6: Yes
A7: Q011 | B7: TF | C7: Iberdrola | D7: Dan Arcangeli | E7: AMI Filmore | F7: 44839 | G7: 44841 | I7: PO Received | J7: No
A8: Q012 | B8: TF | C8: Iberdrola | D8: Dan Arcangeli | E8: AMI Mechanicville, Lockport | F8: 44839 | G8: 44841 | I8: PO Received | J8: No
A9: Q013 | B9: TF | C9: Natures Fynd | D9: Sunny | E9: MCV 3000 Service Kit | F9: 44840 | G9: 44840 | I9: PO Received | J9: Yes
A10: Q014 | B10: JT | C10: Precision Process | D10: Scott Morrow | E10: Inital Design Labor for PPI Line | F10: 44841 | G10: 44841 | H10: 44844 | I10: PO Received | J10: Yes
A11: Q015 | B11: JRW | C11: Engineered Thermal Solutions | D11: Chris Imiola | E11: Cement Cooling Water Tank & Panel Skid | F11: 44840 | G11: 44840 | I11: Not Accepted | J11: No
A12: Q016 | B12: JRW | C12: Sweetworks | D12: Guy Caccavaio | E12: Imperial Line ABB Support | F12: 44841 | G12: 44841 | I12: PO Received | J12: Yes
A13: Q017 | B13: TF | C13: Natures Fynd | D13: Sunny | E13: CPM Service Kit | F13: 44844 | I13: PO Received | J13: Yes
A14: Q018 | B14: JT | C14: Engineered Thermal Solutions | D14: Chuck Marchetta | E14: Kopple PA Cooling Water Controls | F14: 44844 | G14: 44855 | I14: Not Accepted | J14: Yes
A15: Q019 | B15: TF | C15: Lydall | D15: Mike Sanguinito | E15: Machine Guarding for Coating Line | F15: 44846 | I15: PO Received | K15: 2
A16: Q020 | B16: TF | C16: Natures Fynd | D16: Sunny | E16: Steam Trap Spares | F16: 44848 | I16: PO Received | J16: No
A17: Q021 | B17: JT | C17: Hans Kissle | D17: Nick Piccolo | E17: Level Control for Trial Pump | F17: 44848 | G17: 44848 | I17: Not Accepted | J17: Yes
A18: Q022 | B18: TF | C18: Saint- Gobain Niagra | D18: Jeffe Villont | E18: Gel Extruder Abrasive Line | F18: 44854 | I18: Not Accepted | J18: Yes
A19: Q023 | B19: JRW | C19: Saint Gobain Albion | D19: Ron Paeth | E19: FibaTape Packing Line Automation | F19: 44855 | G19: 44855 | I19: Not Accepted | J19: No
A20: Q024 | B20: JRW | C20: Saint Gobain Albion | D20: Ron Paeth | E20: V38 Mixing Line Ingredient Depalletizing Automation | F20: 44858 | G20: 44858 | I20: Not Accepted | J20: No
A21: Q025 | B21: TF | C21: Curaleaf | D21: Luke Burwell | E21: CIP System | F21: 44865 | I21: Not Accepted | J21: Yes
A22: Q026 | B22: JT | C22: Saint Gobain NF | D22: Sean Gokey, Wyatt Wolf | E22: Spray Dryer #2 Recontrol | F22: 44865 | G22: 44866 | I22: Not Accepted | J22: No
A23: Q027 | B23: JRW | C23: Saint Gobain Albion | D23: Ron Paeth | E23: Spackle Line Printing Solution | F23: 44866 | G23: 44866 | I23: Not Accepted | J23: Yes
A24: Q028 | B24: TF | C24: Thrive Foods | D24: Jacob Demaray | E24: Tray Washer Modification | F24: 44867 | I24: PO Received | J24: Yes
A25: Q029 | B25: TF | C25: Thrive Foods | D25: Jacob Demaray | E25: Tray Cart | F25: 44867 | I25: Not Accepted | J25: Yes
A26: Q030 | B26: TF | C26: Chem Aqua | D26: Nick Valente | E26: Nebraska Ozone | F26: 44872 | G26: 44873 | I26: PO Received | J26: Yes
A27: Q031 | B27: JT | C27: Aries | D27: Dan Doyle | E27: Seal Water Overflow Switch | F27: 44872 | G27: 44872 | I27: Not Accepted | J27: Yes
A28: Q032 | B28: TF | C28: Iberdrola | D28: Dan Arcangeli | E28: Bulkheads | F28: 44873 | I28: PO Received | J28: Yes
A29: Q033 | B29: JT | C29: Saint Gobain CertainTeed | D29: John Marciniak | E29: 20:1 Gearbox Difference - In Job 3501 Quote Folder | F29: 44874 | G29: 44874 | I29: PO Received | J29: Yes
A30: Q034 | B30: TF | C30: Chem Aqua | D30: Nick Valente | E30: Spare Parts for Ozone | F30: 44874 | I30: Not Accepted | J30: Yes
A31: Q035 | B31: JT | C31: Engineered Thermal Solutions | D31: Chuck Marchetta | E31: Liberty Tubulars Tower Control Panel | F31: 44883 | G31: 44883 | I31: PO Received | J31: Yes
A32: Q036 | B32: JT | C32: Hans Kissle | D32: Nick Piccolo | E32: MCC and Switch Gear Alternatives | F32: 44887 | I32: Not Accepted | J32: Yes
A33: Q037 | B33: JT | C33: Precision Process | D33: Scott Morrow | E33: T&M Not to exceed update - In Job 3594 Folder | F33: 44894 | G33: 44894 | I33: PO Received | J33: Yes
A34: Q038 | B34: TF | C34: Fresenius Kabi | D34: Andrey Svintozelsky | E34: CIP Flowmeter Replacement | F34: 44897 | I34: PO Received | J34: Yes
A35: Q039 | B35: TF | C35: Avangrid | D35: Dan Arcangeli | E35: SAP Hornell Liberty | F35: 44897 | I35: PO Received | J35: Yes
A36: Q040 | B36: TF | C36: Fresenius Kabi | D36: Andrey Svintozelsky | E36: WIFI Antenna Modification | F36: 44900 | I36: PO Received | J36: Yes
A37: Q041 | B37: TF | C37: Natures Fynd | D37: Vrushank Patel | E37: Filler Drain Leg | F37: 44901 | I37: PO Received | J37: Yes | K37: Rev1
A38: Q042 | B38: JW | C38: McAlpin | D38: John Wilcox | E38: Robot 23 PLC Programming Changes | F38: 44904 | I38: Not Accepted | J38: No
A39: Q043 | B39: JT | C39: Saint Gobain CertainTeed | D39: John Marciniak | E39: Saw Panel Drive Upgrade to Allen Bradley | F39: 44909 | I39: Not Accepted | J39: Yes
A40: Q044 | B40: JT | C40: Engineered Thermal Solutions | D40: Chuck Marchetta | E40: Pump Skid for Cooling Water | F40: 44911 | G40: 44915 | I40: Not Accepted | J40: No
A41: Q045 | B41: JT | C41: Aries | D41: Dan Doyle | E41: Pump Skid for Cooling Water | F41: 44915 | I41: Not Accepted | J41: No
A42: Q046 | B42: JW | C42: Saint Gobain Albion | D42: Ron Paeth | E42: FlexScreen Robot Cover | F42: 44917 | I42: PO Received | J42: Yes
A43: Q047 | B43: JT | C43: McAlpin | D43: Adam Bush | E43: HMI Firmware Upgrade | F43: 44930 | I43: Not Accepted | J43: Yes
A44: Q048 | B44: JW | C44: Sweetworks | D44: Curt Walby | E44: Imperial Line Integration | F44: 44931 | I44: Not Accepted | J44: Yes
A45: Q049 | B45: JT | C45: Aries | D45: Dan Doyle | E45: Historian Enterprise on AWS | F45: 44942 | G45: 44942 | I45: PO Received | J45: Yes
A46: Q050 | B46: JT | C46: Saint Gobain CertainTeed | D46: John Marciniak | E46: Replacement Parts for Vac Panel | F46: 44943 | G46: 44943 | I46: PO Received | J46: Yes
A47: Q051 | B47: TF | C47: Iberdrola | D47: Dan Arcangeli | E47: AMI Project Hornell and Liberty Additional Kits | F47: 44944 | I47: PO Received
A48: Q052 | B48: JT | C48: Saint Gobain Adfors | D48: Mitch Van Lieshout | E48: Knitter trimming drive addition | F48: 44946 | G48: 44951 | I48: Not Accepted | J48: Yes
A49: Q053 | B49: TF | C49: Campbell | D49: Pete Imhoff | E49: Flow Plate Hold Tube | F49: 44951 | I49: PO Received | J49: Yes
A50: Q054 | B50: BV | C50: New Castle Chili | D50: Guy | E50: Additional RTDs with splitters and patch cables | F50: 44951 | G50: 44952 | I50: PO Received | J50: Yes
A51: Q055 | B51: TF | C51: Canopy Foods | D51: Mark Burke | E51: 500 gal and 600 gal Kettles | F51: 44952 | I51: Not Accepted
A52: Q056 | B52: JT/RS | C52: Upstate Rochester | D52: Pat Weed | E52: Filler Safety and Adjustment Upgrades | F52: 44957 | I52: Not Accepted | J52: No
A53: Q057 | B53: JT | C53: Aries | D53: Dan Doyle | E53: Replacement 16A Contactors | F53: 44957 | I53: PO Received | J53: Yes
A54: Q058 | B54: JT | C54: Phinney Tool & Die | D54: Cliff Fuller | E54: AB Safety Sensor | F54: 44945 | G54: 44945 | I54: Not Accepted | J54: No
A55: Q059 | B55: TF | C55: JLM Sales and Marketing | D55: Steve Garren | E55: Kettles | F55: 44958 | I55: Not Accepted
A56: Q060 | B56: JT | C56: Dynisco | D56: Jeff Lundgren | E56: 2022 DAS | F56: 44958 | I56: Not Accepted | J56: No
A57: Q061 | B57: TF | C57: EES Systems | D57: Paco | E57: Interposing Relay Box | F57: 44960 | I57: PO Received
A58: Q062 | B58: TF | C58: Avangrid | D58: Dan Arcangeli | E58: AMI Elmira | F58: 44964 | I58: PO Received
A59: Q063 | B59: TF | C59: Avangrid | D59: Dan Arcangeli | E59: AMI Plattsburg | F59: 44964 | I59: PO Received
A60: Q064 | B60: TF | C60: Avangrid | D60: Dan Arcangeli | E60: AMI Lancaster | F60: 44964 | I60: PO Received
A61: Q065 | B61: TF | C61: Avangrid | D61: Dan Arcangeli | E61: AMI Aubrun | F61: 44964 | I61: PO Received
A62: Q066 | B62: TF | C62: Avangrid | D62: Dan Arcangeli | E62: AMI Oneonta | F62: 44964 | I62: PO Received
A63: Q067 | B63: TF | C63: Avangrid | D63: Dan Arcangeli | E63: AMI Bulkheads | F63: 44965 | I63: PO Received
A64: Q068 | B64: TF | C64: Siagn Industries | D64: Jas Sra | E64: 500 gal Kettle | F64: 44967 | I64: Not Accepted
A65: Q069 | B65: TF | C65: Siagn Industries | D65: Jas Sra | E65: 600 gal Kettle | F65: 44967 | I65: PO Received
A66: Q070 | B66: JT | C66: Phinney Tool & Die | D66: (Rheem) Miguel Garcia, Cliff Fuller | E66: Rheem TS120 Software Update to second press + Industrial PC replacement | F66: 44968 | I66: Not Accepted
A67: Q071 | B67: MM | C67: New Castle Chili | D67: Guy Blume | E67: Modulating Control Valves | F67: 44970 | I67: PO Received
A68: Q072 | B68: JW/SD | C68: Upstate Batavia | D68: Alexander Kinney | E68: 3D Printed Cup Holders | F68: 44971 | I68: PO Received
A69: Q073 | B69: JW | C69: SweetWorks | D69: Curt Walby | E69: Imperial Line Season Startup Support | F69: 44971 | I69: PO Received
A70: Q074 | B70: JT/TF/NE | C70: Iberdrola | D70: David Stowell | E70: QTY 4 24VDC 002I-C (2023) | F70: 44972 | G70: 44974 | I70: PO Received
A71: Q075 | B71: JT/DP | C71: Sweetworks | D71: Curt Walby | E71: Aasted Depositer Level Control | F71: 44970 | I71: Not Accepted | J71: Yes
A72: Q076 | B72: TF | C72: Saint Gobain CertainTeed | D72: John Marciniak | E72: Labor for Z Axis Replacement | F72: 44979 | I72: PO Received
A73: Q077 | B73: TF | C73: Lydall | D73: Bob Taubmann | E73: 2 Door Gate for Coater Line | F73: 44980 | I73: PO Received
A74: Q078 | B74: JT | C74: Concord | D74: Alvin Seenath | E74: Cook Station Raw Material Upgrade | F74: 44986 | I74: PO Received | J74: Yes
A75: Q079 | B75: JW | C75: Buffalo Games | D75: David Rice | E75: Puzzle Packer Line #2 | F75: 44991 | I75: PO Received | J75: Yes
A76: Q080 | B76: JT | C76: Engineered Thermal Solutions | D76: Chuck Marchetta | E76: JST Global Tower Control Panel | F76: 44992 | I76: PO Received | J76: Yes
A77: Q081 | B77: MM | C77: Oatka | D77: Jason Brown | E77: Paletizer Safety Interlock | F77: 44970 | I77: PO Received | J77: Yes
A78: Q082 | B78: RS/MM | C78: Archer Daniels Midland | D78: Vinod Amar | E78: P&ID for Flour bleaching process | F78: 44981 | I78: Not Accepted | J78: Yes
A79: Q083 | B79: MM | C79: New Castle Chili | D79: Mark Grundy | E79: Steam Pressure Relief | F79: 44987 | I79: PO Received | J79: Yes
A80: Q084 | B80: MM | C80: Campbells | D80: Holly Masclans | E80: Blender Valves | F80: 44986 | I80: PO Received | J80: Yes
A81: Q085 | B81: TF | C81: Avangrid | D81: Dan Arcangeli | E81: AMI - Additional Antennas for Liberty SAP | F81: 44995 | I81: PO Received | J81: Yes
A82: Q086 | B82: TF | C82: Avangrid | D82: Dan Arcangeli | E82: AMI- SAP Kits for Filmore | F82: 44995 | I82: PO Received | J82: Yes
A83: Q087 | B83: TF | C83: Avangrid | D83: Dan Arcangeli | E83: AMI SAP Kits for Mechanicville | F83: 44995 | I83: PO Received | J83: Yes
A84: Q088 | B84: TF | C84: Avangrid | D84: Dan Arcangeli | E84: AMI SAP Kits for Elmira | F84: 44995 | I84: PO Received | J84: Yes
A85: Q089 | B85: TF | C85: Avangrid | D85: Dan Arcangeli | E85: AMI SAP Kits for Plattsburgh | F85: 44995 | I85: PO Received | J85: Yes
... A88: Q092 | B88: JT/RS | C88: EJ Gallow | D88: Tom Rice | E88: Hartness Case Packer Recontrol | F88: 44995 | I88: PO Received | J88: Yes
A89: Q093 | B89: TF | C89: Iberdrola | D89: Pete Stritzinger | E89: 50 Large Cabinets | F89: 44998 | I89: Not Accepted
A90: Q094 | B90: JT | C90: Imerys | D90: John Karcz | E90: PLC Upgrade/Backup Plan and Training | F90: 44999 | I90: Not Accepted
A91: Q095 | B91: TF | C91: Freeze-Dry | D91: Tom Burton | E91: Tray Repairs | F91: 45000 | I91: PO Received
A92: Q096 | B92: JT | C92: Brightmark | D92: Erik Darling | E92: Controls work on Boxler PC - reinstalling historian | F92: 45001 | G92: 45002 | I92: Not Accepted | J92: Yes
A93: Q097 | B93: JT | C93: Town of Hartland | D93: Chris Kushner | E93: IT Contract Services for the Town of Hartland | F93: 45001 | G93: 45009 | I93: Not Accepted | J93: No
A94: Q098 | B94: TF | C94: Concord | D94: Alvin Seenath | E94: 150 and 250 gal Kettle | F94: 45001 | I94: PO Received
A95: Q099 | B95: JT | C95: Imerys | D95: John Karcz | E95: Pressure Sensor Programming | F95: 45002 | I95: Not Accepted | J95: Yes
A96: Q0100 | B96: JT | C96: Moley Magnetics | D96: John Moley | E96: NF Air Field Modbus to BacNet Gateway | F96: 45005 | G96: 45006 | I96: PO Received | J96: No
A97: Q0101 | B97: MM/TF/RS | C97: Natures Fynd | D97: Jenna LaRosa | E97: CIP Skid | F97: 45009 | I97: Not Accepted
A98: Q0102 | B98: TF/MM/RS | C98: Natures Fynd | D98: Jenna LaRosa | E98: Pilot Plant Media Make-up | F98: 45009 | I98: PO Received
A99: Q0103 | B99: JW | C99: TurnKey Automation Solutions | D99: Kevin Nicoletta | E99: Dental Trays And Covers | F99: 45009 | I99: PO Received | J99: No
A100: Q0104 | B100: RS | C100: EJ Gallow | D100: Matt Knights | E100: Sanitation Skid - Engineering | F100: 45008 | I100: PO Received
A101: Q0105 | B101: MM | C101: GEA | D101: Joe Connell | E101: Quebec Homogenizer Drawing | F101: 45013 | I101: Not Accepted
A102: Q0106 | B102: TF | C102: Upstate Batavia | D102: Oleg | E102: Drum Cart | F102: 45014 | I102: PO Received
...

Sheet Tasks
B2: Customer | C2: Job | D2: Meeting Code | E2: Assigned To | F2: Priority | G2: Deadline | H2: Task | I2: Status | J2: Cust. Contact | K2: Maturity Timeline | L2: Status Notes
B3: Phinney | C3: 3423 - TS-121 Die Press | D3: PAN, AD | E3: Jon | F3: 1 | G3: 44775 | H3: Billing Status | I3: Archive | L3: Edits reviewed and sent to Christina - invoice pending
B4: Billitier | C4: P0833 - UR Pharm Door PLC | D4: CD, AD | E4: Jon | F4: 1 | G4: 44781 | H4: Billing | I4: Archive | L4: Reached out to Dan Bamann on 8/23 for status
B5: 4015 | C5: R & D | D5: PAN | E5: Brandon, Nick | F5: 1 | G5: 44813 | H5: Perform some market research on what UPS units are on the market that support Lithium-ion battery tech | I5: Done | L5: Have a meeting scheduled with Avangrid on 9/12 to prepare for. No 480V UPS on the market
B6: Aries | C6: 120V Distribution in each MCC | D6: QT | E6: Jon | F6: 2 | G6: 44796 | H6: Quote | I6: Archive
B7: CertainTeed | C7: Macron Gearbox Issue | D7: AD | E7: Jon, Tom | F7: 1 | G7: 44774 | H7: Finish this job NOW! | I7: Done | L7: CO PO came in wrong. Need John M to fix
B8: Precision Process | C8: 3519A - Change Order | D8: AD | E8: Jon | F8: 1 | G8: 44788 | H8: Ensure we do or do not need to bill this | I8: Archive | L8: Don't need to bill
B9: Cedars | C9: 3562 - NF Expansion | D9: PAN | E9: Jon | F9: 1 | G9: 44797 | H9: Order Parts - 6 Prox junction box with cables; 8 Prox Juntion Box with cables; 16 prox Junction Box with cables | I9: Archive
B10: Aries | C10: P0XXX | D10: IT | E10: Jon | F10: 1 | G10: 44812 | H10: Follow up with Aries IT and perform request | I10: Done
B11: Buffalo Games | C11: 3493 - Press 6 Controls System | D11: PAN, AD | E11: Jon | G11: 44768 | H11: Change Order | I11: Archive
B12: McAlpin | C12: CC12 (3508 Robot Duplication) | D12: QT | E12: Brandon | F12: 2 | G12: 44809 | H12: Get an updated cell price from Jim mail and reply to McAlpin's RFQ | I12: Archive | L12: Meeting with customer 9/12 - request for ballpark pricing
B13: Buffalo Games | C13: 3493 - Press 6 Controls System | D13: PAN, AD | E13: Jon | G13: 44769 | H13: Billing Status | I13: Archive
B14: Caldwell | C14: 3494 | D14: PAN, AD | E14: Brandon | G14: 44781 | H14: Billing Status | I14: Archive | L14: Billed
B15: Sweetworks | C15: Delver Depositor Service | D15: AD | E15: Jon | F15: 1 | G15: 44790 | H15: Write service report and bill | I15: Archive | L15: RSA to no-quote depositor.
B16: Campbell | C16: Milwalkee | D16: PAN | E16: Brandon | F16: 1 | G16: 44788 | H16: Transfer PDF to Excel BOM | I16: Archive
B17: Cedars | C17: 3444 - CIP Skid | D17: PAN | E17: Nick | F17: 1 | G17: 44788 | H17: Edit Drawing, add terms for door harness | I17: Archive
B18: Cedars | C18: 3479 - Barcode Scanner | D18: AD | E18: Ricky, Jon | F18: 1 | G18: 44789 | H18: Billing | I18: Done | L18: Pending review with Rick
B19: Aries/Riggs | C19: Billing | D19: AD | E19: Jon | F19: 1 | G19: 44817 | H19: Get us paid | I19: Done | L19: Renus claims payment by end of month
B20: Aries | C20: September Remote Support | D20: QT | E20: Jon | F20: 2 | G20: 44799 | H20: Possible RFQ to support Aries Linden through September Gasifier Run | I20: Done | L20: Get details on date range
B21: Aries | C21: P0XXX | D21: AD | E21: Jon | F21: 2 | G21: 44813 | H21: Write service report for Tri-mer HMI System | I21: Archive | J21: Dan Doyle | L21: Never Done
B22: TakeForm | C22: Dust Collection and VAC Pump Panel | D22: QT | E22: Jon | F22: 1 | G22: 44789 | H22: Quote Panel | I22: Archive
B23: Avangrid | C23: 002I-C Quote Request | D23: QT | E23: Tom, Jon | F23: 1 | G23: 44806 | H23: Send response to avangrid on RFQ for 002I-C | I23: Done | J23: David Stowell
B24: Avangrid | C24: AMI - 3 more locations | D24: QT | E24: Tom | F24: 2 | G24: 44841 | H24: 3 more locations quote | I24: Done
B25: Aries | C25: Review all Billing | D25: AD | E25: Jon | F25: 1 | G25: 44791 | H25: Review all Billing | I25: Archive | L25: Waiting for Christina to review list from James Nesbitt; List has been reviewed once, waiting to review one last report from Brandon
B26: Cedars | C26: 3444 - CIP Skid | D26: ME | E26: Mike | F26: 2 | G26: 44769 | H26: Mechanical Finalization | I26: Archive | L26: Pending update from Ricky
B27: Avangrid | C27: Next two locations | D27: QT | E27: Tom | F27: 1 | G27: 44823 | H27: Did we get a response by 9/19? | I27: Done | L27: Need to review with Rick
B28: Avangrid | C28: Bulk heads | D28: QT | E28: Tom | F28: 4 | G28: 44876 | H28: Follow Up | I28: Done | L28: RFQ out to vendor - will flip when recieved
B29: Iberdrola | C29: 3523 - 100 Cabinet Build | D29: PAN | E29: Nick | F29: 1 | G29: 44788 | H29: Are we supplying Kits? IB102 | I29: Archive | L29: If yes, put together BOM
B30: Avangrid | C30: SAP Bing Can Geneva | D30: QT | E30: Tom | F30: 2 | G30: 44844 | H30: Follow up | I30: Done
B31: ETS | C31: 3567 - Argentina | D31: PAN | E31: Jon | F31: 1 | G31: 44813 | H31: Change Order | I31: Done | L31: Include changes in engineering in change order
B32: Cedars | C32: 3562 - NF Line (3 panels) | D32: PAN | E32: Nick | F32: 1 | G32: 44789 | H32: Verify Stock List | I32: Archive
B33: Iberdrola | C33: 3470 - 30" Cabinet Re-Work | D33: PAN | E33: Nick | F33: 1 | G33: 44795 | H33: In progress, Pete might want these instead of two new cabinets | I33: Archive | L33: New P.O. 3470A, finishing two 30" cabinets for Pete
B34: Baskin Live Stock | C34: QT Follow-up | D34: CD, QT | E34: Jon | F34: 2 | G34: 44788 | H34: QT Follow-up | I34: Archive
B35: Cedars | C35: 3547 - Bag Filler | D35: PAN, AD | E35: Nick | F35: 2 | G35: 44792 | H35: Verify Stock List Status | I35: Archive
B36: Natures Fynd | C36: 3569 - Chiller Cart | D36: AD | E36: Jon | F36: 1 | G36: 44797 | H36: Bill | I36: Done | L36: Checked Numbers 11/9/22 - Christina is clreaed to send Bill to Zach
B37: Cedars | C37: 3554 - GEA Homogenizer Controls | D37: PAN | E37: Nick | F37: 2 | G37: 44792 | H37: Finish Electrical Integration with Homogenizer | I37: Archive | L37: Putting D9P HMI in door
B38: Cedars | C38: 3444 - CIP Skid | D38: PAN | E38: PB | F38: 1 | G38: 44790 | H38: Electrical Finalization | I38: Archive | L38: More changes to electrical design need to be made...again
B39: Cedars | C39: 3554 - Homog 2 | D39: PAN | E39: Nick | F39: 2 | G39: 44792 | H39: Reorder any Canceled Components | I39: Archive | L39: We're not doing this job
B40: Cedars | C40: 3554 - Homog 2 | D40: ME, PAN, AD | E40: Notes | F40: 3 | G40: 44785 | H40: Homog 2 | I40: Archive | L40: We're not doing this job
B41: Cedars | C41: 3444 - CIP Skid | D41: AD | E41: Brandon | F41: 1 | G41: 44802 | H41: Documentation - Consoledate under Cedars | I41: Archive | L41: Network Drawings
B42: Concord | C42: 3417 | D42: AD | E42: Jon | G42: 44783 | H42: Bill | I42: Archive
B43: Concord | C43: 3417 | D43: AD | E43: Jon | G43: 44783 | H43: Change order to finalize | I43: Archive
B44: Cedars | C44: 3578 - 4 x HEPA UV Units | D44: PAN | E44: PB | F44: 1 | G44: 44795 | H44: Assemble HEPA enclosures | I44: Archive | L44: Jason performing some finishing touches / skidding
B45: New Castle Chili | C45: 3576 - New Castle Chili | D45: AD, PAN | E45: Brandon | F45: 1 | G45: 44795 | H45: Follow up on parts delivery | I45: Archive | L45: Report in folder
B46: Brightmark | C46: 3536 - G300 Meter | D46: ME | E46: Mike | F46: 1 | G46: 44795 | H46: Schedule trip to swiss w/ Rick (8/23 afternoon or Wednesday), include Jeremy | I46: Done | L46: Look at the upgrader pad in the same loop
B47: Cedars | C47: CIP 180 and 190 QT | D47: QT | E47: Jon | F47: 1 | G47: 44805 | H47: Write Quote | I47: Archive | L47: Review and approve
B48: Campbell | C48: Milwalkee | D48: QT | E48: Jon | F48: 1 | G48: 44795 | H48: Follow up on QT today | I48: Archive | L48: Lost job
B49: Concord | C49: Cook Station 3 CIP Valves | D49: QT | E49: Jon | F49: 1 | G49: 44788 | H49: Valve Bank Panel Quote | I49: Archive | L49: Debrief with Sean
B50: Aries | C50: Get Osman Paid | D50: AD | E50: Jon | F50: 3 | G50: 44816 | H50: Get Osman Paid | I50: Archive | L50: 10% remaining
B51: Mizkan | C51: Romicon Recontrol | D51: QT | E51: Jon | F51: 1 | G51: 44797 | H51: Schedule a visit to review panel loads for full recontrol | I51: Archive
B52: Cedars | C52: 3479 - Barcode Scanner Panels | D52: PAN | E52: PB | F52: 1 | G52: 44796 | H52: Finish enclosure | I52: Archive | L52: Needs terminal labels, power up, finalization
B53: Phinney | C53: TS120 HMI Support | D53: QT | E53: Jon | F53: 1 | G53: 44775 | H53: HMI Support | I53: Archive
B54: Dynabrade | C54: 3579 - Velcro chopper machine | D54: AD | E54: Tom | F54: 1 | G54: 44788 | H54: Confirm Billing - Make sure we made money | I54: Archive
B55: ETS | C55: 3567 - Argentina | D55: PAN | E55: Jon | G55: 44781 | H55: Review Drawing Markup | I55: Archive
B56: GEA | C56: Kalsec Software Edits | D56: PAN | E56: Jon | F56: 1 | G56: 44795 | H56: Answer Joe's follow up email on software edits and purchase replacement valves | I56: Archive
B57: New Castle Chili | C57: 3576 - New Castle Chili | D57: PAN | E57: Nick | F57: 1 | G57: 44795 | H57: Field Pull Drawing | I57: Archive
B58: Cedars | C58: 3554 - GEA Homogenizer Controls | D58: PAN | E58: PB | F58: 1 | G58: 44788 | H58: Put Subplate in Panel | I58: Archive | L58: Assinging today
B59: RSA | C59: E3616 - 2nd CIP Skid | D59: PAN | E59: Ben | F59: 1 | G59: 45001 | H59: Finalize Panel Design | I59: Done
B60: Iberdrola | C60: 3470A - 2 Cabinets - Final Rev | D60: PAN | E60: Jon | F60: 1 | G60: 44820 | H60: End of Project Checklist - Documentation | I60: Done | L60: No open material?
B61: Iberdrola | C61: 3523 - 100 Cabinet Build | D61: PAN | E61: PB | F61: 1 | G61: 44802 | H61: Subplate Fab | I61: Done | L61: All Nextys equipment delivered. Waiting on remaining Hoffman cabinets. Shipping end of year.
B62: ETS | C62: 3567 - Argentina | D62: PAN | E62: Nick | F62: 1 | G62: 44788 | H62: Follow up on Red Lines | I62: Archive | L62: Meeting next week Wednesday
B63: New Castle Chili | C63: 3576 - 6 Retort System | D63: AD | E63: Jon | F63: 1 | G63: 45002 | H63: Change order for Software work out of scope - potentially include trip cost | I63: Done | L63: No CO needed
B64: Aries | C64: P0XXX | D64: AD, PAN | E64: Jon | F64: 2 | G64: 44816 | H64: Write service report for firewall remote support | I64: Archive | L64: Never Done
B65: Sweetworks | C65: Imperial Line | D65: QT | E65: Jon, Jacob | F65: 1 | G65: 44804 | H65: Answer Guy and Curt on Robot Programming Availability. | I65: Done | J65: Guy Caccavaio
B66: Avient | C66: Acrison Takeover | D66: QT | E66: Jon | F66: 1 | G66: 44839 | H66: Quote Line C Acrison Full Take Over | I66: Done | J66: Aaron Johnson
B67: GEA | C67: Kalsec Software Edits | D67: CD | E67: Jon | F67: 1 | G67: 44775 | H67: Kalsec Software Edits | I67: Archive
B68: Gray/Hans Kisstle | C68: Quote PLC Control | D68: PAN, QT | E68: Jon | F68: 1 | G68: 44788 | H68: BOM Finalization | I68: Archive
B69: New Castle Chili | C69: 3576 - New Castle Chili | D69: PAN | E69: Nick | F69: 1 | G69: 44796 | H69: Electrical Design | I69: Archive
B70: Cedars | C70: 3444 - CIP Skid | D70: AD | E70: Jon | F70: 2 | G70: 44805 | H70: Figure out what to do with the chart recorder | I70: Archive
B71: Iberdrola | C71: 3470A - 2 Cabinets - Final Rev | D71: PAN | E71: Notes | F71: 1 | G71: 44813 | H71: Project Delivery Date | I71: Done | L71: Shipping 10/06/2022
B72: Cedars | C72: 3444 - CIP Skid | D72: ME | E72: Mike | F72: 2 | G72: 44803 | H72: P&ID | I72: Archive | L72: Pending Review
B73: Cedars | C73: 3444 - CIP Skid | D73: AD | E73: Mike | F73: 2 | G73: 44803 | H73: Mechanical Stock List | I73: Archive
B74: ETS | C74: 3540 - Westech | D74: PAN | E74: PB | F74: 1 | G74: 44802 | H74: Finish Panel Build | I74: Archive | L74: Ask Jon about tag placement
B75: Avient | C75: Banbury Full Recontrol | D75: QT | E75: Jon, Nick | F75: 1 | G75: 44839 | H75: Quote Banbury Full Recontrol | I75: Done | J75: Aaron Johnson
B76: Cedars | C76: 3479 - Barcode Scanner | D76: PAN | E76: Nick | F76: 1 | G76: 44803 | H76: Updating electricals with hole seals and cord grip detail | I76: Archive
B77: Gray/Hans Kisstle | C77: Quote PLC Control | D77: PAN, QT | E77: Jon | F77: 1 | G77: 44797 | H77: Compile Various Numbers and writeups into full proposal | I77: Archive | L77: Review QT
B78: Cedars | C78: 3444 - CIP Skid | D78: CD | E78: Ricky | F78: 1 | G78: 44798 | H78: Process/Code Testing | I78: Done
B79: Iberdrola | C79: 3523 - 100 Cabinet Build | D79: PAN | E79: Brandon | G79: 44775 | H79: Follow up with Nextus, Follow up on Sheet Metal Parts | I79: Archive | L79: Eli is working on Sheet Metal Parts. Nextus Responded
B80: Iberdrola | C80: 3523 - 100 Cabinet Build | D80: PAN | E80: Brandon | G80: 44781 | H80: Digitizing Wire List | I80: Archive
B81: ETS | C81: 3567 - Argentina | D81: PAN | E81: Nick | F81: 1 | G81: 44804 | H81: Order Parts | I81: Archive | L81: Switching to 850
B82: Iberdrola | C82: 3470A - 2 Cabinets - Final Rev | D82: PAN | E82: Nick | F82: 1 | G82: 44804 | H82: Nick to reclaim nextus and siemens equipment from example 002I-C Cab | I82: Archive
B83: Cedars | C83: 3562 - NF Line (3 panels) | D83: PAN | E83: PB | F83: 1 | G83: 44806 | H83: Assemble Prox Sensor Junctions | I83: Archive
B84: Iberdrola | C84: 3523 - 100 Cabinet Build | D84: PAN | E84: Jon | F84: 1 | G84: 44785 | H84: Follow up with Christina about the BC | I84: Archive
B85: Cedars | C85: 3444 - CIP Skid | D85: AD | E85: Nick | F85: 2 | G85: 44865 | H85: Electrical Stock List | I85: Archive | L85: Waiting on report from Christina
B86: Iberdrola | C86: 3523 - 100 Cabinet Build | D86: PAN | E86: Brandon | F86: 1 | G86: 44791 | H86: Compare what we have ordered to what needs to be ordered | I86: Archive
B87: Cedars | C87: 3444 - CIP Skid | D87: PAN | E87: Nick | F87: 2 | G87: 44802 | H87: Electrical Drawings | I87: Done | L87: Change Chart Recorder Part Number and send to Silva
B88: ETS | C88: 3567 - Argentina | D88: PAN | E88: Nick | F88: 1 | G88: 44791 | H88: Drawing Updates | I88: Archive
B89: Iberdrola | C89: 3523 - 100 Cabinet Build | D89: PAN | E89: Jon | F89: 3 | G89: 44781 | H89: Come Up with storeage means for 100 subplates | I89: Archive
B90: Iberdrola | C90: 3523 - 100 Cabinet Build | D90: PAN | E90: Brandon | F90: 3 | G90: 44792 | H90: Find Difference in wire estimates from AutoCAD | I90: Archive
B91: Certainteed | C91: 3529 - Saw Panels | D91: PAN | E91: Brandon | F91: 1 | G91: 44803 | H91: Open Material Reports | I91: Archive | L91: Report in folder
B92: Iberdrola | C92: AMI | D92: PAN | E92: Tom | F92: 1 | G92: 44788 | H92: Clarify AMI schedule with Nick and Jon | I92: Archive | L92: Jason will be working on AMI 2-3 days a week opposite of Jonas
B93: Sweetworks | C93: Compressor Recontrol With VFD | D93: QT | E93: Jon | F93: 3 | G93: 44809 | H93: Write Quote | I93: Archive
B94: Brightmark | C94: 3536 - G300 Meter | D94: ME | E94: Mike, Ken | F94: 3 | G94: 44904 | H94: Coordinate Welder pending review | I94: Archive
B95: Buffalo Games | C95: 3493 - Press 6 Controls System | D95: PAN, AD | E95: Nick | G95: 44771 | H95: Stock List | I95: Archive
B96: ETS | C96: 3540 - Westech | D96: PAN | E96: Nick | F96: 1 | G96: 44811 | H96: Powerup Test | I96: Archive
B97: Cedars | C97: 3554 - Homog 1 | D97: ME | E97: Jacob | F97: 1 | G97: 44820 | H97: Take apart the pressure relief valve and document measurements | I97: Archive
B98: Heveron Electric | C98: Support Request - Invertek Drives | D98: PAN | E98: Jon | F98: 2 | G98: 44798 | H98: Call Eric Heveron Back | I98: Archive | L98: Sent email with manual and info - follow up if no feedback
B99: Cedars | C99: 3444 - CIP Skid | D99: CD | E99: Brandon | F99: 1 | G99: 44820 | H99: VBA for CIP values | I99: Archive
B100: Cedars | C100: 3444 - CIP Skid | D100: AD | E100: Nick | F100: 2 | G100: 44805 | H100: Parts List with reference to drawing | I100: Done
B101: Sweetworks | C101: Delver Depositor Recontrol | D101: QT | E101: Jon | F101: 2 | G101: 44792 | H101: Pull together pictures and scope to schedule a meeting with Modern | I101: Archive
...

Sheet Projects
A1: Project Number | B1: Associated Jobs | C1: Created By | D1: Customer | E1: Cust. Contact | F1: Description | G1: Start Date | H1: Due Date | I1: Job Status | J1: In QB | K1: In L Drive | L1: Quote Num | M1: Invoiced | N1: Invoice Date | O1: Notes
A2: 359 | B2: P0961 | C2: JT | D2: Precision Process | E2: Scott Morrow | F2: Inital Engineering for Plating Line | G2: 44838 | I2: Billed | J2: Yes | K2: Yes | L2: Q0009 | M2: 1 | N2: 44841
A3: 2125 | C3: RS | D3: RSA | F3: Apollo Work | G3: ? | J3: Yes
A4: 3289 | C4: RS | D4: HydroGrow | F4: HydroGrow - Header Only | G4: 44456 | J4: Yes
A5: 3352 | C5: TF | D5: RSA | F5: Ozone R&D Work | G5: 44013 | J5: Yes
A6: 3374 | C6: CF | D6: RSA | F6: RSA Continuous Improvement | G6: N/A | J6: Yes
A7: 3398 | C7: RS | D7: RSA | F7: New Building | G7: 44272 | J7: Yes
A8: 3400 | C8: MM | D8: Oatka | F8: SABR Line 1 Slide Doors | G8: 44277 | J8: Yes
A9: 3401 | C9: RS | D9: Poverty Hill | F9: 8" Piping on Sludge Fit | G9: 44277 | J9: Yes
A10: 3402 | C10: SD | D10: Saint Gobain Albion | F10: Machine Return Line Valves | G10: 44284 | I10: Closed | J10: Yes | K10: Yes
A11: 3403 | C11: TF/MM | D11: Oatka | F11: A+R Sweeper Arm Rebuild | G11: 44285 | J11: Yes
A12: 3404 | C12: TF | D12: AEI/Trek | F12: Prototype Burn In Enclosure | G12: 44288 | J12: Yes
A13: 3405 | C13: JT | D13: Mizkan | F13: Wrapper HMI Duplication | G13: 44288 | J13: Yes
A14: 3406 | C14: MM | G14: 44292 | J14: No
A15: 3407 | C15: TF | D15: Oatka | F15: Can Filler Door | G15: 44300 | J15: Yes | L15: Q0TD0312-1
A16: 3408 | C16: TF | D16: Campbell | F16: Flow Panel | G16: 44302 | J16: Yes | L16: QCMP040121
A17: 3409 | C17: RS | D17: Oatka | F17: Filter Screens Gooding Tower | G17: 44302 | J17: Yes | L17: QOTD041621-1
A18: 3410 | C18: RS | D18: Mizkan | F18: Railing | G18: 44306 | J18: Yes
A19: 3411 | C19: JT | D19: Concord | F19: Software Support | G19: 44307 | J19: Yes
A20: 3412 | C20: JW | D20: Novolex | F20: Unloader Bagging Station | G20: 44316 | I20: Closed | J20: No
A21: 3413 | C21: JT | D21: Aries | F21: Panels - Main, Radio and Drive - DeWatering Project | G21: 44322 | J21: Yes
A22: 3414 | D22: Chem Aqua | F22: 4 - Mott's Ozone Units | G22: 44328 | J22: Yes
A23: 3415 | C23: BB | D23: ETS | F23: BOM Creator | G23: 44335 | J23: Yes
A24: 3416 | C24: JT | D24: Moley Magnetics | F24: Batching System Software Dev | G24: 44398 | J24: No
A25: 3417 | C25: JT | D25: Concord | F25: PLC 5 Upgrade CS3 | G25: 44337 | J25: Yes
A26: 3418 | C26: RS | D26: Campbell | F26: Tote Batching Skid | G26: 44337 | J26: No
A27: 3419 | C27: MP | D27: Oatka | F27: CIP Panel | G27: 44341 | J27: Yes | L27: QOTD032621
A28: 3420 | C28: MP | D28: Cardinal | F28: Hydrolic Tank Repair | G28: 44342 | J28: Yes
A29: 3421 | C29: MP/MM | D29: Saint Gobain Albion | F29: Tanks/Racks | G29: 44342 | I29: Closed | J29: No
A30: 3422 | C30: GF | D30: Mizkan | F30: Evaluation of Containment Phasel | G30: 44357 | J30: Yes
A31: 3423 | D31: Phinney | F31: Die Press Control Panel | G31: 44361 | J31: No | K31: Yes | L31: PO#11247
A32: 3424 | C32: TJF | D32: ETS | F32: Control Panel w/VFD | G32: 44369 | J32: No | L32: QETS022621-1
A33: 3425 | C33: TJF | D33: Nature's Fynd Yodelay | F33: Yodelay Filler Hood | G33: 44371 | J33: No | L33: QNFD062321
A34: 3426 | C34: Ed/CF | D34: Concord | F34: Homogenizer Repair | G34: 44371 | J34: Yes
A35: 3427 | C35: MP | D35: Brightmark | F35: Piping Quote | G35: 44372 | J35: Yes
A36: 3428 | C36: MM | D36: Oatka | F36: Gaurd Doors | G36: 44376 | J36: Yes
A37: 3429 | C37: TF | D37: AEI/Trek | F37: PCS Bench Enclosure | G37: 44383 | J37: No
A38: 3430 | C38: SD | D38: Oatka | F38: Rosemont Lvl Switch + Engineering | G38: 44384 | I38: Closed | J38: No | K38: Yes
A39: 3431 | C39: MM | D39: Mizkan | F39: Lyndonville Bottling Tanks P&ID | G39: 44391 | J39: No
A40: 3432 | C40: TJF | D40: Mizkan | F40: Cleaning Knife & Gaurding | G40: 44393 | J40: No | L40: QM2K071621
A41: 3433 | C41: JT | D41: Riggs | F41: Linden Water Ingress Evaluation | G41: 44397 | J41: Yes
A42: 3434 | C42: TJF | D42: Nature's Fynd | F42: Media Room Phase II B | G42: 44400 | J42: No
A43: 3435 | C43: RSJ | D43: St. Gobain | F43: Goating Removal Pre Eng | G43: 44400 | J43: Yes | L43: QSBG062821
A44: 3436 | C44: NE | D44: ETS | F44: Control Panel Fox Tox | G44: 44403 | J44: Yes | L44: QETS061521
A45: 3437 | C45: Bob | D45: Cedars | F45: Auger Repair Mi---- | G45: 44403 | J45: Yes
A46: 3438 | C46: Bob | D46: Cardinal | F46: 7091 S Hydrolic Resevoir | G46: 44403 | J46: Yes | L46: QCAR072121
A47: 3439 | C47: CP | D47: Brightmark | F47: Trending PLC @ Yellowjacket Sites | G47: 44410 | J47: Yes | L47: QBRT060221
A48: 3440 | C48: MM | D48: Oatka | F48: Case Reject Line Modifications | G48: 44411 | J48: Yes | L48: QOTD072221
A49: 3441 | C49: MM | D49: Aries | F49: Orifice Plates | G49: 44417 | J49: Yes | L49: QACE072621
A50: 3442 | C50: SD | D50: Aries | F50: Wireless Mesh Network | G50: 44418 | I50: Closed | J50: Yes | K50: Yes
A51: 3443 | C51: JT | D51: Riggs | F51: Linden Water Remediation | G51: 44419 | J51: Yes
A52: 3444 | C52: NE | D52: RSA | F52: RSA CIP Skid | G52: 44421 | J52: Yes | M52: 100 | N52: 45023
A53: 3445 | C53: RS | D53: Aries | F53: Aries Kearny P&ID Review | G53: 44421 | J53: Yes
A54: 3446 | C54: RS | D54: Cedars | F54: Kraft | G54: 44409 | J54: Yes
A55: 3447 | D55: Oatka | F55: Cardboard Bailer | G55: 44432 | I55: Closed | J55: No | K55: Yes
A56: 3448 | C56: RS | D56: Xylem | F56: Uncoiler | G56: 44434 | J56: No
A57: 3449 | C57: NE | D57: SGB Certainteed | F57: Picket Puller Panels | G57: 44439 | J57: No
A58: 3450 | C58: JT | D58: Nature's Fynd | F58: CINT SCCR Upgrade | G58: 44439 | J58: Yes | L58: QNFD8162021
A59: 3451 | C59: RS | D59: Qualitrol | F59: Install of Test Racks | G59: 44440 | J59: Yes | L59: QQTH060721
A60: 3452 | C60: RS | D60: Upstate Batavia | F60: Robotic Packer Parts | G60: 44456 | J60: Yes
A61: 3453 | C61: JT | D61: Aries | F61: Integrate and Startup | G61: 44456 | J61: Yes
A62: 3454 | C62: RS | D62: Cedars | F62: Dunkaroo General Mills | G62: 44461 | J62: Yes
A63: 3455 | C63: TJF | D63: Nature's Fynd | F63: Fermenter Rebuild | G63: 44466 | J63: No
A64: 3456 | C64: TJF | D64: Nature's Fynd | F64: Filler Valve Replacement | G64: 44467 | J64: No | L64: QNFD091621-Rev1
A65: 3457 | C65: RS | D65: Cedars | F65: Onsite RS | G65: 44473 | J65: Yes
A66: 3458 | D66: Campbell | F66: 4 Port Flow Panel | G66: 44475 | J66: No | K66: Yes
A67: 3459 | C67: NE/JT | D67: Moley | F67: Remote PuMP Control parts+eng | G67: 44475 | J67: Yes
A68: 3460 | C68: MP | D68: Upstate Batavia | F68: Robotic Arm Eng Tooling | G68: 44475 | J68: Yes
A69: 3461 | C69: Bob | D69: Upstate Batavia | F69: Slip Sheet hift assembly | G69: 44475 | J69: No
A70: 3462 | C70: RS | D70: Oatka | F70: Waste Water | G70: 44477 | J70: Yes
A71: 3463 | C71: RS | D71: Canandagua Winery | F71: Blender Room Controls | G71: 44480 | J71: Yes
A72: 3464 | C72: TJF | D72: CertainTeed | F72: Vacuum Panel Build | G72: 44483 | J72: No | L72: QSGBB082021
A73: 3465 | C73: JRW | D73: Upstate Batavia | F73: Eoat Tubing Design + Build | G73: 44487 | J73: No
A74: 3466 | C74: MM | D74: Oatka | F74: Retort Work Platform and Stair Case #2 | G74: 44491 | J74: Yes
A75: 3467 | C75: RSJ | D75: Nature's Fynd | F75: Yogurt and Cream Cheese Cedars Install | G75: 44495 | I75: Billed | J75: Yes | M75: 100 | N75: 44537
A76: 3468 | C76: JT/BB | D76: Aries | F76: Linden Startup | G76: 44502 | J76: Yes
A77: 3469 | C77: TJF | D77: Avangrid | F77: Mercury Cabinet Engineering | G77: 44505 | J77: Yes
A78: 3470 | C78: TJF | D78: Avangrid | F78: Mercury Prototype Cabinet | G78: 44505 | J78: Yes
A79: 3471 | C79: RS | D79: Mizkan | F79: Rotary Filler Lower Frame Only | G79: 44508 | J79: Yes | L79: RSA090221
A80: 3472 | C80: TJF | D80: AEI/Trek | F80: PCS Enclosure - 2 | G80: 44515 | J80: Yes | L80: 4010954
A81: 3473 | C81: TJF | D81: Nature's Fynd | F81: AMFEC Blender | G81: 44518 | J81: Yes
A82: 3474 | C82: RS | D82: Upstate Batavia | F82: Osgood Laner Converyor Controls | G82: 44518 | J82: No
A83: 3475 | C83: TJF | D83: Xerox | F83: W216 Blender Additive Feeder | G83: 44519 | J83: Yes | M83: 50, 50% | N83: 4/13, 10/13
A84: 3476 | C84: JT/MP | D84: Phinney | F84: PCC HMI Devleopment | G84: 44522 | J84: Yes
A85: 3477 | C85: RS | D85: Oatka | F85: Truck Parking Lot Expansion | G85: 44526 | J85: Yes
A86: 3478 | D86: Campbell | F86: 3" 4-port flow panel | G86: 44530 | J86: No | K86: Yes
A87: 3479 | C87: TJF | D87: Cedars | F87: Barcode Scanner | G87: 44531 | I87: Billed | J87: Yes | M87: 100 | N87: 44922
A88: 3480 | C88: RS | D88: Midland Asphalt | F88: Meter and Piping Upgrade | G88: 44531 | I88: Billed | J88: Yes | M88: 100 | N88: 44910
A89: 3481 | C89: MM | D89: Brightmark | F89: G500 Meter Upgrades | G89: 44531 | J89: No | L89: QBMK070721Rev1
A90: 3482 | C90: MP/RS | D90: Oatka | F90: Stack tank Safety Stair Add | G90: 44531 | I90: Billed | J90: Yes | L90: Q080321RevC | M90: 100 | N90: 44918
A91: 3483 | C91: MP/CF | F91: Rental | G91: 44531 | J91: No
A92: 3484 | C92: CF | D92: Chem Aqua | F92: 2022 Roch Tech Ozone Units | G92: 44532 | J92: No
A93: 3485 | C93: CF | D93: Denkavit | F93: 2022 Ozone Unit | G93: 44532 | J93: No
A94: 3486 | C94: CF | D94: Mizkan | F94: 2022 Ozone Unit | G94: 44532 | J94: No
A95: 3487 | C95: CF | D95: Rochester Midland | F95: 2022 Ozone Unit | G95: 44532 | J95: No
A96: 3488 | C96: NE | D96: GEA | F96: Kalsec Homogenizer | G96: 44536 | J96: No
A97: 3489 | C97: MM | D97: Oatka | F97: North Exit ??? | G97: 44538 | J97: Yes
A98: 3490 | C98: RS | D98: CP1 | F98: 21-1202 Build Assembly | G98: 44539 | J98: Yes
A99: 3491 | C99: MM | D99: Oatka | F99: 2-Platform palletizer | G99: 44545 | I99: Billed | J99: Yes | L99: Q080621 | M99: 100 | N99: 44918
A100: 3492 | C100: TF | D100: ??? | F100: Weld Cell | G100: 44545 | J100: Yes
...

Sheet Parts and Services
A1: Job Number | B1: Created By | C1: Customer | D1: Cust. Contact | E1: Description | F1: Vendor | G1: Start Date | H1: Due Date | I1: Job Status | J1: In QB | K1: In L Drive | L1: Quote Num | M1: Invoiced | N1: Date Inv | O1: Notes
A2: P0738 | B2: RDS | C2: Cedar's | E2: Twin Scre Pump and Seals | G2: 44585
A3: P0773 | B3: SD | C3: Cedar's | E3: Cream cheese pump RMA | G3: 44627 | I3: Billed | J3: Yes | M3: 100 | N3: 44887
A4: P0800 | B4: SD | C4: Cedar's | E4: Baldor Motor | G4: 44657 | I4: Billed
A5: P0801 | B5: SD | C5: Campbell | E5: VFDs | G5: 44658 | I5: Billed | J5: Yes | L5: CN10256369 | M5: 100 | N5: 44852
A6: P0802 | B6: SD | C6: Big Ditch | E6: Coriolis Meter | G6: 44658 | I6: Billed | L6: 2022-04-07-MBK-01
A7: P0803 | B7: RSJ | C7: Nature's Fynd | E7: Single Homogenizer Trail | G7: 44659 | J7: Yes | M7: 100 | N7: 44873
A8: P0804 | B8: SD | C8: CSC Sugar | E8: Spare Parts | G8: 44662 | I8: Billed
A9: P0805 | B9: SD | C9: Northeast Industrial | E9: Photosensor | G9: 44663 | I9: Billed | L9: 204574
A10: P0806 | B10: TF | C10: Upstate Batavia | E10: Vacuum Ejector | G10: 44664 | M10: 100 | N10: 44771
A11: P0807 | B11: SD | C11: Northeast Industrial | E11: Photosensors and Relays | G11: 44664 | I11: Billed | L11: 204629
A12: P0808 | B12: SD | C12: Heartfelt | E12: Steam Generator | G12: 44693 | I12: Billed | L12: N/A
A13: P0809 | B13: MP/TF | C13: Certainteed | E13: Jaw Gripper | G13: 44665 | L13: 3002128449
A14: P0810 | B14: MP | C14: Cedar's | E14: RTD and Wiring Puck | G14: 44666 | L14: 1-193200
A15: P0811 | B15: SD | C15: Campbell | E15: Proxes and Brackets | G15: 44669 | I15: Billed | L15: 4505446099
A16: P0812 | B16: SD | C16: Northeast Industrial | E16: Push Buttons | G16: 44670 | I16: Billed | L16: 204788
A17: P0813 | B17: KR | C17: Midland Asphalt | E17: Bray 920930 w Mounting Units | G17: 44670
A18: P0814 | B18: SD | C18: LiDestri | E18: Valves | G18: 44672 | I18: Billed | L18: 332519
A19: P0815 | B19: SD | C19: Oatka | E19: Parts | G19: 44672 | I19: Billed | L19: P0202276
A20: P0816 | B20: SD | C20: LiDestri | E20: Valves | G20: 44672 | I20: Billed | L20: 332534
A21: P0817 | B21: SD | C21: EJ Gallo | E21: ILM RMA | G21: 44678 | I21: Billed | J21: Yes | M21: 100 | N21: 44925
A22: P0818 | B22: SD | C22: Upstate Batavia | E22: Turk Prox Plugs | G22: 44678 | I22: Billed | L22: 27001C016-0000-000
A23: P0819 | B23: SD | C23: Upstate w/ Seneca | E23: Manifold Parts | G23: 44680 | I23: Billed
A24: P0820 | B24: KR | C24: Midland Asphalt | E24: Grease Gun | G24: 44683
A25: P0821 | B25: RSJ | C25: Nature's Fynd | G25: 44683 | I25: Billed | J25: Yes | M25: 100 | N25: 44873
A26: P0822 | B26: SD | C26: CSC Sugar | E26: Seal Kits | G26: 44685 | I26: Billed | L26: 54-2653
A27: P0823 | B27: SD | C27: CSC Sugar | E27: Seal Kits 2 | G27: 44685 | I27: Billed | L27: 54-2660
A28: P0824 | B28: SD | C28: Upstate Batavia | E28: Pneumatic Cylinder | G28: 44686 | I28: Billed | L28: 2700K027-0000-000
A29: P0825 | B29: SD | C29: Northeast Industrial | E29: Sensagaurd | G29: 44687 | I29: Billed | L29: 205541
A30: P0826 | B30: SD | C30: Campbell | E30: Gantes and Elbows | G30: 44687 | I30: Billed | L30: 4505467239
A31: P0827 | B31: MP/RSJ/JT | C31: Certainteed | E31: 1762-OF4 | G31: 44691
A32: P0828 | B32: SD | C32: Northeast Industrial | E32: PWRFLX Drives / HP | G32: 44692 | I32: Billed | J32: Yes | L32: 205751 | M32: 100 | N32: 44907 | O32: 3 drives remain partial billing 5,9,11
A33: P0829 | B33: SD | C33: Concord | E33: Gear Drive | G33: 44692 | I33: Billed | L33: CP2201
A34: P0830 | B34: SD | C34: Richards Equipment | E34: Seal Kit | G34: 44693 | I34: Billed | L34: 20222489
A35: P0831 | B35: JT | C35: Qualitrol | E35: Onsite Service | G35: 44693 | J35: Yes | L35: Onsite Controls | M35: 1 | N35: 44875
A36: P0832 | B36: SD | C36: Heartfelt | E36: Steam Generation | G36: 44693 | I36: Billed
A37: P0833 | B37: JT | C37: Billitier Electrical | E37: ??? Onsite | G37: 44693
A38: P0834 | B38: MM | C38: Heveron Electric | E38: Dryer Plate | G38: 44693
A39: P0835 | B39: SD | C39: Cedar's | E39: Pressure Trans + RTDs | G39: 44697 | I39: Billed | L39: 1-193964
A40: P0836 | B40: SD | C40: LiDestri | E40: Angle Seat Valves | G40: 44697 | I40: Billed | L40: 333766
A41: P0837 | B41: SD | C41: Upstate Batavia | E41: Banner Parts | G41: 44698 | I41: Billed | L41: 27001055-0000-000
A42: P0838 | B42: JW/JT | C42: Dynabrade | E42: Onsite ?? | G42: 44698 | L42: P0034616
A43: P0839 | B43: SD | C43: CSC Sugar | E43: LFV Pump | G43: 44698 | I43: Billed | L43: 54-2794
A44: P0840 | B44: SD | C44: Nature's Fynd | E44: UV Parts | G44: 44700 | I44: Billed | L44: 13196963
A45: P0841 | B45: BB | C45: Phinney Tool and Die | E45: SICK Sensors | G45: 44701 | L45: 12114 | M45: 100 | N45: 45036
A46: P0842 | B46: SD | C46: Cedar's | E46: RTDs | G46: 44704 | I46: Billed | L46: 1-194127
A47: P0843 | B47: SD | C47: CSC Sugar | E47: Stark Compression | G47: 44704 | I47: Billed | L47: 54-2819
A48: P0844 | B48: SD | C48: Cedar's | E48: Control Top | G48: 44705 | I48: Billed
A49: P0845 | B49: RSJ | C49: Nature's Fynd | E49: Hope Panelview | G49: 44705
A50: P0846 | B50: SD | C50: Cedar's | E50: Panelviews | G50: 44706 | I50: Billed | L50: 1-194187
A51: P0847 | B51: SD | C51: St. Gobain Buffalo | E51: New Powered Rollers | G51: 44706 | I51: Billed | L51: 3002207927
A52: P0848 | B52: SD | G52: 44706 | I52: Billed
A53: P0849 | B53: JT/NE | C53: ETS | E53: Pushbutton Parts | G53: 44708
A54: P0850 | B54: SD | C54: Northeast Industrial | E54: Angle Seat Valves | G54: 44712 | I54: Billed | L54: 206489
A55: P0851 | B55: SD | C55: Cedar's | E55: RTD Pucks | G55: 44714 | I55: Billed | L55: 1-1-94424
A56: P0852 | B56: SD | C56: Concord | E56: Plate Heat Exchanger | G56: 44715 | I56: Billed | L56: BH-15291-4220159
A57: P0853 | B57: SD | C57: Upstate Batavia | E57: Inductive Sensor | G57: 44715 | I57: Billed | L57: 27001079-0000-000
A58: P0854 | B58: SD | C58: Campbell | E58: Sink + Parts | G58: 44718 | I58: Billed | L58: 4505503624
A59: P0855 | B59: SD | C59: Richards Equipment | E59: Seal Kits | G59: 44720 | I59: Billed | L59: 20223017
A60: P0856 | B60: MP/SD | C60: Upstate | E60: Photoeye | G60: 44725 | L60: 27001091
A61: P0857 | B61: SD | C61: Saint Gobain | E61: Powerflex VFD | G61: 44728 | I61: Billed | L61: 4551056888
A62: P0858 | B62: MP/SD | C62: Cedar's | E62: Adapter Kit | G62: 44729 | I62: Billed | J62: Yes | M62: 100 | N62: 44924
A63: P0859 | B63: SD | C63: Richards Equipment | E63: Seal Kits | G63: 44729 | I63: Billed | L63: 20222952
A64: P0860 | B64: JRW | C64: Sweetworks | E64: Wrapping Machine Service | G64: 44725
A65: P0861 | B65: SD | C65: Northeast Industrial | E65: Photosensors | G65: 44732 | I65: Billed | L65: 207317
A66: P0862 | B66: SD | C66: Upstate Niagra | E66: Solenoids | G66: 44732 | I66: Billed | L66: 36927
A67: P0863 | B67: SD | C67: EJ Gallo | E67: I/O Parts | G67: 44733 | I67: Billed | L67: 8000084613
A68: P0864 | B68: RDS | C68: Mizkan Lyndonville | E68: Romicon PLC | G68: 44733
A69: P0865 | B69: SD | C69: Concord | E69: RTDs | G69: 44733 | I69: Billed | L69: BH-15345-42200170
A70: P0866 | B70: SD | C70: Cedar's | E70: Nagmeter and Eaton | G70: 44734 | I70: Billed
A71: P0867 | B71: JT/CF | C71: Buffalo Games | E71: Cable | G71: 44735
A72: P0868 | B72: SD | C72: Northeast Industrial | E72: Shortening Plugs | G72: 44736 | I72: Billed | L72: 207562
A73: P0869 | B73: SD | C73: Sweetworks | E73: Regulating Valve | G73: 44736 | I73: Billed | L73: P-119466
A74: P0870 | B74: SD | C74: LiDestri | E74: Angle Seat Valves | G74: 44736 | I74: Billed | L74: 335601
A75: P0871 | B75: NE/DP | C75: Precious Plate | E75: Service Line 21 Logic | G75: 44737
A76: P0872 | B76: JT | C76: Buffalo Games | E76: Studio 5000 Gaurdlogix | G76: 44739 | L76: 24381
A77: P0873 | B77: MP | C77: Richards Equipment | E77: Ampco Seals | G77: 44739
A78: P0874 | B78: MP/SD | C78: Cedar's | E78: LMI Pump | G78: 44740 | L78: 1-195223
A79: P0875 | B79: MP/SD | C79: Northeast Industrial | E79: 4&6 HP Drives | G79: 44740 | L79: 207672
A80: P0876 | B80: MP/SD | C80: Empire | E80: HUF Panels | G80: 44742 | L80: 230260
A81: P0877 | B81: BB | C81: Aries | E81: SQL Reporting | G81: 44743
A82: P0878 | B82: JW | C82: Dynabrade | E82: Face Washer | G82: 44748 | I82: Billed | J82: Yes | L82: P0035479 | M82: 1 | N82: 44873
A83: P0879 | B83: SD | C83: Aries | E83: Trans Drivers | G83: 44748 | I83: Billed | L83: ALPO-00343 | M83: 1 | N83: 44859
A84: P0880 | B84: SD | C84: Cedar's | E84: Seal Kits | G84: 44748 | I84: Billed | L84: TBD/Per Rick | M84: 1 | N84: 44844
A85: P0881 | B85: SD | C85: Heveron Electric | E85: 15HP VFD | G85: 44749 | I85: Billed
A86: P0882 | B86: JW/JT | C86: Dynabrade | E86: Conveyors | G86: 44750
A87: P0883 | B87: SD | C87: Aries | G87: 44750 | I87: Billed | L87: RSA070722-0099
A88: P0884 | B88: SD | C88: Concord | E88: Broken Disconnect Handle | G88: 44753 | I88: Billed | L88: BH-15398-4220170
A89: P0885 | B89: SD | C89: Northeast Industrial | E89: Seal Kits | G89: 44753 | I89: Billed | L89: 208114
A90: P0886 | B90: SD | C90: Cedar's | E90: Graco Saniforce Pump | G90: 44753 | I90: Billed | L90: 1-195531
A91: P0887 | B91: SD | C91: Cedar's | E91: ZC2 Pump | G91: 44753 | I91: Billed | L91: 1-195528
A92: P0888 | B92: SD | C92: EJ Gallo | E92: Micro 800 | G92: 44753 | I92: Billed | L92: 8000086128
A93: P0889 | B93: MP/JT | C93: Poverty Hill Farm | E93: Cable, Uthm ??, turn RSA | G93: 44755
A94: P0890 | B94: JW | C94: Dynabrade | E94: Conveyor | G94: 44755 | I94: Billed | J94: Yes | M94: 100 | N94: 44901
A95: P0891 | B95: JT | C95: Sweetworks | E95: S.C. | G95: 44755
A96: P0892 | B96: SD | C96: Campbell | E96: Valve Repair Set | G96: 44755 | I96: Billed | L96: 4505546159
A97: P0893 | B97: SD | C97: Cedar's | E97: Seal Kit | G97: 44756 | I97: Billed | M97: 1 | N97: 44844
A98: P0894 | B98: SD | C98: Richards Equipment | E98: Seal Kit | G98: 44757 | I98: Billed
A99: P0895 | B99: JT/CF | C99: Aries | E99: Software SQL | G99: 44757 | L99: ALPO-00244
A100: P0896 | B100: JT | C100: Aries | E100: Ition Work | G100: 44760
...

Sheet Checks and Stats
B1: Team Allocation: | D1: =SUM(D4:D1048576)/SUM($C$4:$C$1048576) -> #DIV/0! | F1: =SUM(F4:F1048576)/SUM($C$4:$C$1048576) -> #DIV/0! | H1: =SUM(H4:H1048576)/SUM($C$4:$C$1048576) -> #DIV/0! | J1: =SUM(J4:J1048576)/SUM($C$4:$C$1048576) -> #DIV/0! | S1: Task Completion
C2: Goal: | D2: 0.2 | F2: 0.6 | H2: 0.2 | S2: Open | T2: =COUNTIF(Table1[Status],'Checks and Stats'!S2)/(COUNTA(Table1[Status])-COUNTIF(Table1[Status],"Archive")) -> 0
B3: Assigned To | C3: Num Tasks | D3: Critical | F3: High | H3: Medium | J3: Low | L3: Assigned To | M3: Critical | N3: High | O3: Medium | P3: Low | S3: Done | T3: =COUNTIF(Table1[Status],'Checks and Stats'!S3)/(COUNTA(Table1[Status])-COUNTIF(Table1[Status],"Archive")) -> 1
B4: {=_xlfn.UNIQUE(_xlfn.TEXTSPLIT(_xlfn.UNIQUE(Table1[Assigned To]),","))} -> Jon | C4: =COUNTIF(Table1[Assigned To],"*" & $B4) + COUNTIF(Table1[Assigned To],$B4 & ",*") - COUNTIFS(Table1[Assigned To],"*" & $B4,Table1[Status],"Archive") - COUNTIFS(Table1[Assigned To],$B4 & ",*",Table1[Status],"Archive") - COUNTIFS(Table1[Assigned To],"*" & $B4,Table1[Status],"Done") - COUNTIFS(Table1[Assigned To],$B4 & ",*",Table1[Status],"Done") -> 0 | D4: =COUNTIFS(Table1[Assigned To],"*" & $B4,Table1[Priority],"1") + COUNTIFS(Table1[Assigned To],$B4 & ",*",Table1[Priority],"1") - COUNTIFS(Table1[Assigned To],"*" & $B4,Table1[Status],"Archive",Table1[Priority],"1") - COUNTIFS(Table1[Assigned To],$B4 & ",*",Table1[Status],"Archive",Table1[Priority],"1") - COUNTIFS(Table1[Assigned To],"*" & $B4,Table1[Status],"Done",Table1[Priority],"1") - COUNTIFS(Table1[Assigned To],$B4 & ",*",Table1[Status],"Done",Table1[Priority],"1") -> 0 | E4: =D4/C4 -> #DIV/0! | F4: =COUNTIFS(Table1[Assigned To],"*" & $B4,Table1[Priority],"2") + COUNTIFS(Table1[Assigned To],$B4 & ",*",Table1[Priority],"2") - COUNTIFS(Table1[Assigned To],"*" & $B4,Table1[Status],"Archive",Table1[Priority],"2") - COUNTIFS(Table1[Assigned To],$B4 & ",*",Table1[Status],"Archive",Table1[Priority],"2") - COUNTIFS(Table1[Assigned To],"*" & $B4,Table1[Status],"Done",Table1[Priority],"2") - COUNTIFS(Table1[Assigned To],$B4 & ",*",Table1[Status],"Done",Table1[Priority],"2") -> 0 | G4: =F4/C4 -> #DIV/0! | H4: =COUNTIFS(Table1[Assigned To],"*" & $B4,Table1[Priority],"3") + COUNTIFS(Table1[Assigned To],$B4 & ",*",Table1[Priority],"3") - COUNTIFS(Table1[Assigned To],"*" & $B4,Table1[Status],"Archive",Table1[Priority],"3") - COUNTIFS(Table1[Assigned To],$B4 & ",*",Table1[Status],"Archive",Table1[Priority],"3") - COUNTIFS(Table1[Assigned To],"*" & $B4,Table1[Status],"Done",Table1[Priority],"3") - COUNTIFS(Table1[Assigned To],$B4 & ",*",Table1[Status],"Done",Table1[Priority],"3") -> 0 | I4: =H4/C4 -> #DIV/0! | J4: =COUNTIFS(Table1[Assigned To],"*" & $B4,Table1[Priority],"4") + COUNTIFS(Table1[Assigned To],$B4 & ",*",Table1[Priority],"4") - COUNTIFS(Table1[Assigned To],"*" & $B4,Table1[Status],"Archive",Table1[Priority],"4") - COUNTIFS(Table1[Assigned To],$B4 & ",*",Table1[Status],"Archive",Table1[Priority],"4") - COUNTIFS(Table1[Assigned To],"*" & $B4,Table1[Status],"Done",Table1[Priority],"4") - COUNTIFS(Table1[Assigned To],$B4 & ",*",Table1[Status],"Done",Table1[Priority],"4") -> 0 | K4: =J4/C4 -> #DIV/0! | L4: {=_xlfn.UNIQUE(_xlfn._xlws.FILTER(Table1[Assigned To],Table1[Assigned To]<>""))} -> Jon | M4: =IF(AND((D4/$C4)>D$2+0.05,$C4>4),2,IF(AND((D4/$C4)>D$2,$C4>4),1,0)) -> #DIV/0! | N4: =IF(AND((F4/$C4)>F$2+0.05,$C4>4),2,IF(AND((F4/$C4)>F$2,$C4>4),1,0)) -> #DIV/0! | O4: =IF(AND((H4/$C4)>H$2+0.05,$C4>4),2,IF(AND((H4/$C4)>H$2,$C4>4),1,0)) -> #DIV/0! | P4: =IF(AND((J4/$C4)>J$2,$C4>4),1,0) -> #DIV/0! | Q4: =SUM(D4,F4,H4,J4) -> 0 | S4: External Dependency | T4: =COUNTIF(Table1[Status],'Checks and Stats'!S4)/(COUNTA(Table1[Status])-COUNTIF(Table1[Status],"Archive")) -> 0
B5: Brandon | C5: =COUNTIF(Table1[Assigned To],"*" & $B5) + COUNTIF(Table1[Assigned To],$B5 & ",*") - COUNTIFS(Table1[Assigned To],"*" & $B5,Table1[Status],"Archive") - COUNTIFS(Table1[Assigned To],$B5 & ",*",Table1[Status],"Archive") - COUNTIFS(Table1[Assigned To],"*" & $B5,Table1[Status],"Done") - COUNTIFS(Table1[Assigned To],$B5 & ",*",Table1[Status],"Done") -> 0 | D5: =COUNTIFS(Table1[Assigned To],"*" & $B5,Table1[Priority],"1") + COUNTIFS(Table1[Assigned To],$B5 & ",*",Table1[Priority],"1") - COUNTIFS(Table1[Assigned To],"*" & $B5,Table1[Status],"Archive",Table1[Priority],"1") - COUNTIFS(Table1[Assigned To],$B5 & ",*",Table1[Status],"Archive",Table1[Priority],"1") - COUNTIFS(Table1[Assigned To],"*" & $B5,Table1[Status],"Done",Table1[Priority],"1") - COUNTIFS(Table1[Assigned To],$B5 & ",*",Table1[Status],"Done",Table1[Priority],"1") -> 0 | E5: =IF(C5=0,0,D5/C5) -> 0 | F5: =COUNTIFS(Table1[Assigned To],"*" & $B5,Table1[Priority],"2") + COUNTIFS(Table1[Assigned To],$B5 & ",*",Table1[Priority],"2") - COUNTIFS(Table1[Assigned To],"*" & $B5,Table1[Status],"Archive",Table1[Priority],"2") - COUNTIFS(Table1[Assigned To],$B5 & ",*",Table1[Status],"Archive",Table1[Priority],"2") - COUNTIFS(Table1[Assigned To],"*" & $B5,Table1[Status],"Done",Table1[Priority],"2") - COUNTIFS(Table1[Assigned To],$B5 & ",*",Table1[Status],"Done",Table1[Priority],"2") -> 0 | G5: =IF(C5=0,0,F5/C5) -> 0 | H5: =COUNTIFS(Table1[Assigned To],"*" & $B5,Table1[Priority],"3") + COUNTIFS(Table1[Assigned To],$B5 & ",*",Table1[Priority],"3") - COUNTIFS(Table1[Assigned To],"*" & $B5,Table1[Status],"Archive",Table1[Priority],"3") - COUNTIFS(Table1[Assigned To],$B5 & ",*",Table1[Status],"Archive",Table1[Priority],"3") - COUNTIFS(Table1[Assigned To],"*" & $B5,Table1[Status],"Done",Table1[Priority],"3") - COUNTIFS(Table1[Assigned To],$B5 & ",*",Table1[Status],"Done",Table1[Priority],"3") -> 0 | I5: =IF(C5=0,0,H5/C5) -> 0 | J5: =COUNTIFS(Table1[Assigned To],"*" & $B5,Table1[Priority],"4") + COUNTIFS(Table1[Assigned To],$B5 & ",*",Table1[Priority],"4") - COUNTIFS(Table1[Assigned To],"*" & $B5,Table1[Status],"Archive",Table1[Priority],"4") - COUNTIFS(Table1[Assigned To],$B5 & ",*",Table1[Status],"Archive",Table1[Priority],"4") - COUNTIFS(Table1[Assigned To],"*" & $B5,Table1[Status],"Done",Table1[Priority],"4") - COUNTIFS(Table1[Assigned To],$B5 & ",*",Table1[Status],"Done",Table1[Priority],"4") -> 0 | K5: =IF(C5=0,0,J5/C5) -> 0 | L5: Brandon, Nick | M5: =IF(AND((D5/$C5)>D$2+0.05,$C5>4),2,IF(AND((D5/$C5)>D$2,$C5>4),1,0)) -> #DIV/0! | N5: =IF(AND((F5/$C5)>F$2+0.05,$C5>4),2,IF(AND((F5/$C5)>F$2,$C5>4),1,0)) -> #DIV/0! | O5: =IF(AND((H5/$C5)>H$2+0.05,$C5>4),2,IF(AND((H5/$C5)>H$2,$C5>4),1,0)) -> #DIV/0! | P5: =IF(AND((J5/$C5)>J$2,$C5>4),1,0) -> #DIV/0! | Q5: =SUM(D5,F5,H5,J5) -> 0 | S5: Internal Dependency | T5: =COUNTIF(Table1[Status],'Checks and Stats'!S5)/(COUNTA(Table1[Status])-COUNTIF(Table1[Status],"Archive")) -> 0
B6: Nick | C6: =COUNTIF(Table1[Assigned To],"*" & $B6) + COUNTIF(Table1[Assigned To],$B6 & ",*") - COUNTIFS(Table1[Assigned To],"*" & $B6,Table1[Status],"Archive") - COUNTIFS(Table1[Assigned To],$B6 & ",*",Table1[Status],"Archive") - COUNTIFS(Table1[Assigned To],"*" & $B6,Table1[Status],"Done") - COUNTIFS(Table1[Assigned To],$B6 & ",*",Table1[Status],"Done") -> 0 | D6: =COUNTIFS(Table1[Assigned To],"*" & $B6,Table1[Priority],"1") + COUNTIFS(Table1[Assigned To],$B6 & ",*",Table1[Priority],"1") - COUNTIFS(Table1[Assigned To],"*" & $B6,Table1[Status],"Archive",Table1[Priority],"1") - COUNTIFS(Table1[Assigned To],$B6 & ",*",Table1[Status],"Archive",Table1[Priority],"1") - COUNTIFS(Table1[Assigned To],"*" & $B6,Table1[Status],"Done",Table1[Priority],"1") - COUNTIFS(Table1[Assigned To],$B6 & ",*",Table1[Status],"Done",Table1[Priority],"1") -> 0 | E6: =IF(C6=0,0,D6/C6) -> 0 | F6: =COUNTIFS(Table1[Assigned To],"*" & $B6,Table1[Priority],"2") + COUNTIFS(Table1[Assigned To],$B6 & ",*",Table1[Priority],"2") - COUNTIFS(Table1[Assigned To],"*" & $B6,Table1[Status],"Archive",Table1[Priority],"2") - COUNTIFS(Table1[Assigned To],$B6 & ",*",Table1[Status],"Archive",Table1[Priority],"2") - COUNTIFS(Table1[Assigned To],"*" & $B6,Table1[Status],"Done",Table1[Priority],"2") - COUNTIFS(Table1[Assigned To],$B6 & ",*",Table1[Status],"Done",Table1[Priority],"2") -> 0 | G6: =IF(C6=0,0,F6/C6) -> 0 | H6: =COUNTIFS(Table1[Assigned To],"*" & $B6,Table1[Priority],"3") + COUNTIFS(Table1[Assigned To],$B6 & ",*",Table1[Priority],"3") - COUNTIFS(Table1[Assigned To],"*" & $B6,Table1[Status],"Archive",Table1[Priority],"3") - COUNTIFS(Table1[Assigned To],$B6 & ",*",Table1[Status],"Archive",Table1[Priority],"3") - COUNTIFS(Table1[Assigned To],"*" & $B6,Table1[Status],"Done",Table1[Priority],"3") - COUNTIFS(Table1[Assigned To],$B6 & ",*",Table1[Status],"Done",Table1[Priority],"3") -> 0 | I6: =IF(C6=0,0,H6/C6) -> 0 | J6: =COUNTIFS(Table1[Assigned To],"*" & $B6,Table1[Priority],"4") + COUNTIFS(Table1[Assigned To],$B6 & ",*",Table1[Priority],"4") - COUNTIFS(Table1[Assigned To],"*" & $B6,Table1[Status],"Archive",Table1[Priority],"4") - COUNTIFS(Table1[Assigned To],$B6 & ",*",Table1[Status],"Archive",Table1[Priority],"4") - COUNTIFS(Table1[Assigned To],"*" & $B6,Table1[Status],"Done",Table1[Priority],"4") - COUNTIFS(Table1[Assigned To],$B6 & ",*",Table1[Status],"Done",Table1[Priority],"4") -> 0 | K6: =IF(C6=0,0,J6/C6) -> 0 | L6: Jon, Tom | M6: =IF(AND((D6/$C6)>D$2+0.05,$C6>4),2,IF(AND((D6/$C6)>D$2,$C6>4),1,0)) -> #DIV/0! | N6: =IF(AND((F6/$C6)>F$2+0.05,$C6>4),2,IF(AND((F6/$C6)>F$2,$C6>4),1,0)) -> #DIV/0! | O6: =IF(AND((H6/$C6)>H$2+0.05,$C6>4),2,IF(AND((H6/$C6)>H$2,$C6>4),1,0)) -> #DIV/0! | P6: =IF(AND((J6/$C6)>J$2,$C6>4),1,0) -> #DIV/0! | Q6: =SUM(D6,F6,H6,J6) -> 0 | S6: In Progress | T6: =COUNTIF(Table1[Status],'Checks and Stats'!S6)/(COUNTA(Table1[Status])-COUNTIF(Table1[Status],"Archive")) -> 0
B7: Ricky | C7: =COUNTIF(Table1[Assigned To],"*" & $B7) + COUNTIF(Table1[Assigned To],$B7 & ",*") - COUNTIFS(Table1[Assigned To],"*" & $B7,Table1[Status],"Archive") - COUNTIFS(Table1[Assigned To],$B7 & ",*",Table1[Status],"Archive") - COUNTIFS(Table1[Assigned To],"*" & $B7,Table1[Status],"Done") - COUNTIFS(Table1[Assigned To],$B7 & ",*",Table1[Status],"Done") -> 0 | D7: =COUNTIFS(Table1[Assigned To],"*" & $B7,Table1[Priority],"1") + COUNTIFS(Table1[Assigned To],$B7 & ",*",Table1[Priority],"1") - COUNTIFS(Table1[Assigned To],"*" & $B7,Table1[Status],"Archive",Table1[Priority],"1") - COUNTIFS(Table1[Assigned To],$B7 & ",*",Table1[Status],"Archive",Table1[Priority],"1") - COUNTIFS(Table1[Assigned To],"*" & $B7,Table1[Status],"Done",Table1[Priority],"1") - COUNTIFS(Table1[Assigned To],$B7 & ",*",Table1[Status],"Done",Table1[Priority],"1") -> 0 | E7: =IF(C7=0,0,D7/C7) -> 0 | F7: =COUNTIFS(Table1[Assigned To],"*" & $B7,Table1[Priority],"2") + COUNTIFS(Table1[Assigned To],$B7 & ",*",Table1[Priority],"2") - COUNTIFS(Table1[Assigned To],"*" & $B7,Table1[Status],"Archive",Table1[Priority],"2") - COUNTIFS(Table1[Assigned To],$B7 & ",*",Table1[Status],"Archive",Table1[Priority],"2") - COUNTIFS(Table1[Assigned To],"*" & $B7,Table1[Status],"Done",Table1[Priority],"2") - COUNTIFS(Table1[Assigned To],$B7 & ",*",Table1[Status],"Done",Table1[Priority],"2") -> 0 | G7: =IF(C7=0,0,F7/C7) -> 0 | H7: =COUNTIFS(Table1[Assigned To],"*" & $B7,Table1[Priority],"3") + COUNTIFS(Table1[Assigned To],$B7 & ",*",Table1[Priority],"3") - COUNTIFS(Table1[Assigned To],"*" & $B7,Table1[Status],"Archive",Table1[Priority],"3") - COUNTIFS(Table1[Assigned To],$B7 & ",*",Table1[Status],"Archive",Table1[Priority],"3") - COUNTIFS(Table1[Assigned To],"*" & $B7,Table1[Status],"Done",Table1[Priority],"3") - COUNTIFS(Table1[Assigned To],$B7 & ",*",Table1[Status],"Done",Table1[Priority],"3") -> 0 | I7: =IF(C7=0,0,H7/C7) -> 0 | J7: =COUNTIFS(Table1[Assigned To],"*" & $B7,Table1[Priority],"4") + COUNTIFS(Table1[Assigned To],$B7 & ",*",Table1[Priority],"4") - COUNTIFS(Table1[Assigned To],"*" & $B7,Table1[Status],"Archive",Table1[Priority],"4") - COUNTIFS(Table1[Assigned To],$B7 & ",*",Table1[Status],"Archive",Table1[Priority],"4") - COUNTIFS(Table1[Assigned To],"*" & $B7,Table1[Status],"Done",Table1[Priority],"4") - COUNTIFS(Table1[Assigned To],$B7 & ",*",Table1[Status],"Done",Table1[Priority],"4") -> 0 | K7: =IF(C7=0,0,J7/C7) -> 0 | L7: Brandon | M7: =IF(AND((D7/$C7)>D$2+0.05,$C7>4),2,IF(AND((D7/$C7)>D$2,$C7>4),1,0)) -> #DIV/0! | N7: =IF(AND((F7/$C7)>F$2+0.05,$C7>4),2,IF(AND((F7/$C7)>F$2,$C7>4),1,0)) -> #DIV/0! | O7: =IF(AND((H7/$C7)>H$2+0.05,$C7>4),2,IF(AND((H7/$C7)>H$2,$C7>4),1,0)) -> #DIV/0! | P7: =IF(AND((J7/$C7)>J$2,$C7>4),1,0) -> #DIV/0! | Q7: =SUM(D7,F7,H7,J7) -> 0
B8: Tom | C8: =COUNTIF(Table1[Assigned To],"*" & $B8) + COUNTIF(Table1[Assigned To],$B8 & ",*") - COUNTIFS(Table1[Assigned To],"*" & $B8,Table1[Status],"Archive") - COUNTIFS(Table1[Assigned To],$B8 & ",*",Table1[Status],"Archive") - COUNTIFS(Table1[Assigned To],"*" & $B8,Table1[Status],"Done") - COUNTIFS(Table1[Assigned To],$B8 & ",*",Table1[Status],"Done") -> 0 | D8: =COUNTIFS(Table1[Assigned To],"*" & $B8,Table1[Priority],"1") + COUNTIFS(Table1[Assigned To],$B8 & ",*",Table1[Priority],"1") - COUNTIFS(Table1[Assigned To],"*" & $B8,Table1[Status],"Archive",Table1[Priority],"1") - COUNTIFS(Table1[Assigned To],$B8 & ",*",Table1[Status],"Archive",Table1[Priority],"1") - COUNTIFS(Table1[Assigned To],"*" & $B8,Table1[Status],"Done",Table1[Priority],"1") - COUNTIFS(Table1[Assigned To],$B8 & ",*",Table1[Status],"Done",Table1[Priority],"1") -> 0 | E8: =IF(C8=0,0,D8/C8) -> 0 | F8: =COUNTIFS(Table1[Assigned To],"*" & $B8,Table1[Priority],"2") + COUNTIFS(Table1[Assigned To],$B8 & ",*",Table1[Priority],"2") - COUNTIFS(Table1[Assigned To],"*" & $B8,Table1[Status],"Archive",Table1[Priority],"2") - COUNTIFS(Table1[Assigned To],$B8 & ",*",Table1[Status],"Archive",Table1[Priority],"2") - COUNTIFS(Table1[Assigned To],"*" & $B8,Table1[Status],"Done",Table1[Priority],"2") - COUNTIFS(Table1[Assigned To],$B8 & ",*",Table1[Status],"Done",Table1[Priority],"2") -> 0 | G8: =IF(C8=0,0,F8/C8) -> 0 | H8: =COUNTIFS(Table1[Assigned To],"*" & $B8,Table1[Priority],"3") + COUNTIFS(Table1[Assigned To],$B8 & ",*",Table1[Priority],"3") - COUNTIFS(Table1[Assigned To],"*" & $B8,Table1[Status],"Archive",Table1[Priority],"3") - COUNTIFS(Table1[Assigned To],$B8 & ",*",Table1[Status],"Archive",Table1[Priority],"3") - COUNTIFS(Table1[Assigned To],"*" & $B8,Table1[Status],"Done",Table1[Priority],"3") - COUNTIFS(Table1[Assigned To],$B8 & ",*",Table1[Status],"Done",Table1[Priority],"3") -> 0 | I8: =IF(C8=0,0,H8/C8) -> 0 | J8: =COUNTIFS(Table1[Assigned To],"*" & $B8,Table1[Priority],"4") + COUNTIFS(Table1[Assigned To],$B8 & ",*",Table1[Priority],"4") - COUNTIFS(Table1[Assigned To],"*" & $B8,Table1[Status],"Archive",Table1[Priority],"4") - COUNTIFS(Table1[Assigned To],$B8 & ",*",Table1[Status],"Archive",Table1[Priority],"4") - COUNTIFS(Table1[Assigned To],"*" & $B8,Table1[Status],"Done",Table1[Priority],"4") - COUNTIFS(Table1[Assigned To],$B8 & ",*",Table1[Status],"Done",Table1[Priority],"4") -> 0 | K8: =IF(C8=0,0,J8/C8) -> 0 | L8: Nick | M8: =IF(AND((D8/$C8)>D$2+0.05,$C8>4),2,IF(AND((D8/$C8)>D$2,$C8>4),1,0)) -> #DIV/0! | N8: =IF(AND((F8/$C8)>F$2+0.05,$C8>4),2,IF(AND((F8/$C8)>F$2,$C8>4),1,0)) -> #DIV/0! | O8: =IF(AND((H8/$C8)>H$2+0.05,$C8>4),2,IF(AND((H8/$C8)>H$2,$C8>4),1,0)) -> #DIV/0! | P8: =IF(AND((J8/$C8)>J$2,$C8>4),1,0) -> #DIV/0! | Q8: =SUM(D8,F8,H8,J8) -> 0
B9: Mike | C9: =COUNTIF(Table1[Assigned To],"*" & $B9) + COUNTIF(Table1[Assigned To],$B9 & ",*") - COUNTIFS(Table1[Assigned To],"*" & $B9,Table1[Status],"Archive") - COUNTIFS(Table1[Assigned To],$B9 & ",*",Table1[Status],"Archive") - COUNTIFS(Table1[Assigned To],"*" & $B9,Table1[Status],"Done") - COUNTIFS(Table1[Assigned To],$B9 & ",*",Table1[Status],"Done") -> 0 | D9: =COUNTIFS(Table1[Assigned To],"*" & $B9,Table1[Priority],"1") + COUNTIFS(Table1[Assigned To],$B9 & ",*",Table1[Priority],"1") - COUNTIFS(Table1[Assigned To],"*" & $B9,Table1[Status],"Archive",Table1[Priority],"1") - COUNTIFS(Table1[Assigned To],$B9 & ",*",Table1[Status],"Archive",Table1[Priority],"1") - COUNTIFS(Table1[Assigned To],"*" & $B9,Table1[Status],"Done",Table1[Priority],"1") - COUNTIFS(Table1[Assigned To],$B9 & ",*",Table1[Status],"Done",Table1[Priority],"1") -> 0 | E9: =IF(C9=0,0,D9/C9) -> 0 | F9: =COUNTIFS(Table1[Assigned To],"*" & $B9,Table1[Priority],"2") + COUNTIFS(Table1[Assigned To],$B9 & ",*",Table1[Priority],"2") - COUNTIFS(Table1[Assigned To],"*" & $B9,Table1[Status],"Archive",Table1[Priority],"2") - COUNTIFS(Table1[Assigned To],$B9 & ",*",Table1[Status],"Archive",Table1[Priority],"2") - COUNTIFS(Table1[Assigned To],"*" & $B9,Table1[Status],"Done",Table1[Priority],"2") - COUNTIFS(Table1[Assigned To],$B9 & ",*",Table1[Status],"Done",Table1[Priority],"2") -> 0 | G9: =IF(C9=0,0,F9/C9) -> 0 | H9: =COUNTIFS(Table1[Assigned To],"*" & $B9,Table1[Priority],"3") + COUNTIFS(Table1[Assigned To],$B9 & ",*",Table1[Priority],"3") - COUNTIFS(Table1[Assigned To],"*" & $B9,Table1[Status],"Archive",Table1[Priority],"3") - COUNTIFS(Table1[Assigned To],$B9 & ",*",Table1[Status],"Archive",Table1[Priority],"3") - COUNTIFS(Table1[Assigned To],"*" & $B9,Table1[Status],"Done",Table1[Priority],"3") - COUNTIFS(Table1[Assigned To],$B9 & ",*",Table1[Status],"Done",Table1[Priority],"3") -> 0 | I9: =IF(C9=0,0,H9/C9) -> 0 | J9: =COUNTIFS(Table1[Assigned To],"*" & $B9,Table1[Priority],"4") + COUNTIFS(Table1[Assigned To],$B9 & ",*",Table1[Priority],"4") - COUNTIFS(Table1[Assigned To],"*" & $B9,Table1[Status],"Archive",Table1[Priority],"4") - COUNTIFS(Table1[Assigned To],$B9 & ",*",Table1[Status],"Archive",Table1[Priority],"4") - COUNTIFS(Table1[Assigned To],"*" & $B9,Table1[Status],"Done",Table1[Priority],"4") - COUNTIFS(Table1[Assigned To],$B9 & ",*",Table1[Status],"Done",Table1[Priority],"4") -> 0 | K9: =IF(C9=0,0,J9/C9) -> 0 | L9: Ricky, Jon | M9: =IF(AND((D9/$C9)>D$2+0.05,$C9>4),2,IF(AND((D9/$C9)>D$2,$C9>4),1,0)) -> #DIV/0! | N9: =IF(AND((F9/$C9)>F$2+0.05,$C9>4),2,IF(AND((F9/$C9)>F$2,$C9>4),1,0)) -> #DIV/0! | O9: =IF(AND((H9/$C9)>H$2+0.05,$C9>4),2,IF(AND((H9/$C9)>H$2,$C9>4),1,0)) -> #DIV/0! | P9: =IF(AND((J9/$C9)>J$2,$C9>4),1,0) -> #DIV/0! | Q9: =SUM(D9,F9,H9,J9) -> 0
B10: PB | C10: =COUNTIF(Table1[Assigned To],"*" & $B10) + COUNTIF(Table1[Assigned To],$B10 & ",*") - COUNTIFS(Table1[Assigned To],"*" & $B10,Table1[Status],"Archive") - COUNTIFS(Table1[Assigned To],$B10 & ",*",Table1[Status],"Archive") - COUNTIFS(Table1[Assigned To],"*" & $B10,Table1[Status],"Done") - COUNTIFS(Table1[Assigned To],$B10 & ",*",Table1[Status],"Done") -> 0 | D10: =COUNTIFS(Table1[Assigned To],"*" & $B10,Table1[Priority],"1") + COUNTIFS(Table1[Assigned To],$B10 & ",*",Table1[Priority],"1") - COUNTIFS(Table1[Assigned To],"*" & $B10,Table1[Status],"Archive",Table1[Priority],"1") - COUNTIFS(Table1[Assigned To],$B10 & ",*",Table1[Status],"Archive",Table1[Priority],"1") - COUNTIFS(Table1[Assigned To],"*" & $B10,Table1[Status],"Done",Table1[Priority],"1") - COUNTIFS(Table1[Assigned To],$B10 & ",*",Table1[Status],"Done",Table1[Priority],"1") -> 0 | E10: =IF(C10=0,0,D10/C10) -> 0 | F10: =COUNTIFS(Table1[Assigned To],"*" & $B10,Table1[Priority],"2") + COUNTIFS(Table1[Assigned To],$B10 & ",*",Table1[Priority],"2") - COUNTIFS(Table1[Assigned To],"*" & $B10,Table1[Status],"Archive",Table1[Priority],"2") - COUNTIFS(Table1[Assigned To],$B10 & ",*",Table1[Status],"Archive",Table1[Priority],"2") - COUNTIFS(Table1[Assigned To],"*" & $B10,Table1[Status],"Done",Table1[Priority],"2") - COUNTIFS(Table1[Assigned To],$B10 & ",*",Table1[Status],"Done",Table1[Priority],"2") -> 0 | G10: =IF(C10=0,0,F10/C10) -> 0 | H10: =COUNTIFS(Table1[Assigned To],"*" & $B10,Table1[Priority],"3") + COUNTIFS(Table1[Assigned To],$B10 & ",*",Table1[Priority],"3") - COUNTIFS(Table1[Assigned To],"*" & $B10,Table1[Status],"Archive",Table1[Priority],"3") - COUNTIFS(Table1[Assigned To],$B10 & ",*",Table1[Status],"Archive",Table1[Priority],"3") - COUNTIFS(Table1[Assigned To],"*" & $B10,Table1[Status],"Done",Table1[Priority],"3") - COUNTIFS(Table1[Assigned To],$B10 & ",*",Table1[Status],"Done",Table1[Priority],"3") -> 0 | I10: =IF(C10=0,0,H10/C10) -> 0 | J10: =COUNTIFS(Table1[Assigned To],"*" & $B10,Table1[Priority],"4") + COUNTIFS(Table1[Assigned To],$B10 & ",*",Table1[Priority],"4") - COUNTIFS(Table1[Assigned To],"*" & $B10,Table1[Status],"Archive",Table1[Priority],"4") - COUNTIFS(Table1[Assigned To],$B10 & ",*",Table1[Status],"Archive",Table1[Priority],"4") - COUNTIFS(Table1[Assigned To],"*" & $B10,Table1[Status],"Done",Table1[Priority],"4") - COUNTIFS(Table1[Assigned To],$B10 & ",*",Table1[Status],"Done",Table1[Priority],"4") -> 0 | K10: =IF(C10=0,0,J10/C10) -> 0 | L10: Tom, Jon | M10: =IF(AND((D10/$C10)>D$2+0.05,$C10>4),2,IF(AND((D10/$C10)>D$2,$C10>4),1,0)) -> #DIV/0! | N10: =IF(AND((F10/$C10)>F$2+0.05,$C10>4),2,IF(AND((F10/$C10)>F$2,$C10>4),1,0)) -> #DIV/0! | O10: =IF(AND((H10/$C10)>H$2+0.05,$C10>4),2,IF(AND((H10/$C10)>H$2,$C10>4),1,0)) -> #DIV/0! | P10: =IF(AND((J10/$C10)>J$2,$C10>4),1,0) -> #DIV/0! | Q10: =SUM(D10,F10,H10,J10) -> 0
B11: Notes | C11: =COUNTIF(Table1[Assigned To],"*" & $B11) + COUNTIF(Table1[Assigned To],$B11 & ",*") - COUNTIFS(Table1[Assigned To],"*" & $B11,Table1[Status],"Archive") - COUNTIFS(Table1[Assigned To],$B11 & ",*",Table1[Status],"Archive") - COUNTIFS(Table1[Assigned To],"*" & $B11,Table1[Status],"Done") - COUNTIFS(Table1[Assigned To],$B11 & ",*",Table1[Status],"Done") -> 0 | D11: =COUNTIFS(Table1[Assigned To],"*" & $B11,Table1[Priority],"1") + COUNTIFS(Table1[Assigned To],$B11 & ",*",Table1[Priority],"1") - COUNTIFS(Table1[Assigned To],"*" & $B11,Table1[Status],"Archive",Table1[Priority],"1") - COUNTIFS(Table1[Assigned To],$B11 & ",*",Table1[Status],"Archive",Table1[Priority],"1") - COUNTIFS(Table1[Assigned To],"*" & $B11,Table1[Status],"Done",Table1[Priority],"1") - COUNTIFS(Table1[Assigned To],$B11 & ",*",Table1[Status],"Done",Table1[Priority],"1") -> 0 | E11: =IF(C11=0,0,D11/C11) -> 0 | F11: =COUNTIFS(Table1[Assigned To],"*" & $B11,Table1[Priority],"2") + COUNTIFS(Table1[Assigned To],$B11 & ",*",Table1[Priority],"2") - COUNTIFS(Table1[Assigned To],"*" & $B11,Table1[Status],"Archive",Table1[Priority],"2") - COUNTIFS(Table1[Assigned To],$B11 & ",*",Table1[Status],"Archive",Table1[Priority],"2") - COUNTIFS(Table1[Assigned To],"*" & $B11,Table1[Status],"Done",Table1[Priority],"2") - COUNTIFS(Table1[Assigned To],$B11 & ",*",Table1[Status],"Done",Table1[Priority],"2") -> 0 | G11: =IF(C11=0,0,F11/C11) -> 0 | H11: =COUNTIFS(Table1[Assigned To],"*" & $B11,Table1[Priority],"3") + COUNTIFS(Table1[Assigned To],$B11 & ",*",Table1[Priority],"3") - COUNTIFS(Table1[Assigned To],"*" & $B11,Table1[Status],"Archive",Table1[Priority],"3") - COUNTIFS(Table1[Assigned To],$B11 & ",*",Table1[Status],"Archive",Table1[Priority],"3") - COUNTIFS(Table1[Assigned To],"*" & $B11,Table1[Status],"Done",Table1[Priority],"3") - COUNTIFS(Table1[Assigned To],$B11 & ",*",Table1[Status],"Done",Table1[Priority],"3") -> 0 | I11: =IF(C11=0,0,H11/C11) -> 0 | J11: =COUNTIFS(Table1[Assigned To],"*" & $B11,Table1[Priority],"4") + COUNTIFS(Table1[Assigned To],$B11 & ",*",Table1[Priority],"4") - COUNTIFS(Table1[Assigned To],"*" & $B11,Table1[Status],"Archive",Table1[Priority],"4") - COUNTIFS(Table1[Assigned To],$B11 & ",*",Table1[Status],"Archive",Table1[Priority],"4") - COUNTIFS(Table1[Assigned To],"*" & $B11,Table1[Status],"Done",Table1[Priority],"4") - COUNTIFS(Table1[Assigned To],$B11 & ",*",Table1[Status],"Done",Table1[Priority],"4") -> 0 | K11: =IF(C11=0,0,J11/C11) -> 0 | L11: Tom | M11: =IF(AND((D11/$C11)>D$2+0.05,$C11>4),2,IF(AND((D11/$C11)>D$2,$C11>4),1,0)) -> #DIV/0! | N11: =IF(AND((F11/$C11)>F$2+0.05,$C11>4),2,IF(AND((F11/$C11)>F$2,$C11>4),1,0)) -> #DIV/0! | O11: =IF(AND((H11/$C11)>H$2+0.05,$C11>4),2,IF(AND((H11/$C11)>H$2,$C11>4),1,0)) -> #DIV/0! | P11: =IF(AND((J11/$C11)>J$2,$C11>4),1,0) -> #DIV/0! | Q11: =SUM(D11,F11,H11,J11) -> 0
B12: Ben | C12: =COUNTIF(Table1[Assigned To],"*" & $B12) + COUNTIF(Table1[Assigned To],$B12 & ",*") - COUNTIFS(Table1[Assigned To],"*" & $B12,Table1[Status],"Archive") - COUNTIFS(Table1[Assigned To],$B12 & ",*",Table1[Status],"Archive") - COUNTIFS(Table1[Assigned To],"*" & $B12,Table1[Status],"Done") - COUNTIFS(Table1[Assigned To],$B12 & ",*",Table1[Status],"Done") -> 0 | D12: =COUNTIFS(Table1[Assigned To],"*" & $B12,Table1[Priority],"1") + COUNTIFS(Table1[Assigned To],$B12 & ",*",Table1[Priority],"1") - COUNTIFS(Table1[Assigned To],"*" & $B12,Table1[Status],"Archive",Table1[Priority],"1") - COUNTIFS(Table1[Assigned To],$B12 & ",*",Table1[Status],"Archive",Table1[Priority],"1") - COUNTIFS(Table1[Assigned To],"*" & $B12,Table1[Status],"Done",Table1[Priority],"1") - COUNTIFS(Table1[Assigned To],$B12 & ",*",Table1[Status],"Done",Table1[Priority],"1") -> 0 | E12: =IF(C12=0,0,D12/C12) -> 0 | F12: =COUNTIFS(Table1[Assigned To],"*" & $B12,Table1[Priority],"2") + COUNTIFS(Table1[Assigned To],$B12 & ",*",Table1[Priority],"2") - COUNTIFS(Table1[Assigned To],"*" & $B12,Table1[Status],"Archive",Table1[Priority],"2") - COUNTIFS(Table1[Assigned To],$B12 & ",*",Table1[Status],"Archive",Table1[Priority],"2") - COUNTIFS(Table1[Assigned To],"*" & $B12,Table1[Status],"Done",Table1[Priority],"2") - COUNTIFS(Table1[Assigned To],$B12 & ",*",Table1[Status],"Done",Table1[Priority],"2") -> 0 | G12: =IF(C12=0,0,F12/C12) -> 0 | H12: =COUNTIFS(Table1[Assigned To],"*" & $B12,Table1[Priority],"3") + COUNTIFS(Table1[Assigned To],$B12 & ",*",Table1[Priority],"3") - COUNTIFS(Table1[Assigned To],"*" & $B12,Table1[Status],"Archive",Table1[Priority],"3") - COUNTIFS(Table1[Assigned To],$B12 & ",*",Table1[Status],"Archive",Table1[Priority],"3") - COUNTIFS(Table1[Assigned To],"*" & $B12,Table1[Status],"Done",Table1[Priority],"3") - COUNTIFS(Table1[Assigned To],$B12 & ",*",Table1[Status],"Done",Table1[Priority],"3") -> 0 | I12: =IF(C12=0,0,H12/C12) -> 0 | J12: =COUNTIFS(Table1[Assigned To],"*" & $B12,Table1[Priority],"4") + COUNTIFS(Table1[Assigned To],$B12 & ",*",Table1[Priority],"4") - COUNTIFS(Table1[Assigned To],"*" & $B12,Table1[Status],"Archive",Table1[Priority],"4") - COUNTIFS(Table1[Assigned To],$B12 & ",*",Table1[Status],"Archive",Table1[Priority],"4") - COUNTIFS(Table1[Assigned To],"*" & $B12,Table1[Status],"Done",Table1[Priority],"4") - COUNTIFS(Table1[Assigned To],$B12 & ",*",Table1[Status],"Done",Table1[Priority],"4") -> 0 | K12: =IF(C12=0,0,J12/C12) -> 0 | L12: Mike | M12: =IF(AND((D12/$C12)>D$2+0.05,$C12>4),2,IF(AND((D12/$C12)>D$2,$C12>4),1,0)) -> #DIV/0! | N12: =IF(AND((F12/$C12)>F$2+0.05,$C12>4),2,IF(AND((F12/$C12)>F$2,$C12>4),1,0)) -> #DIV/0! | O12: =IF(AND((H12/$C12)>H$2+0.05,$C12>4),2,IF(AND((H12/$C12)>H$2,$C12>4),1,0)) -> #DIV/0! | P12: =IF(AND((J12/$C12)>J$2,$C12>4),1,0) -> #DIV/0! | Q12: =SUM(D12,F12,H12,J12) -> 0
B13: Jacob | C13: =COUNTIF(Table1[Assigned To],"*" & $B13) + COUNTIF(Table1[Assigned To],$B13 & ",*") - COUNTIFS(Table1[Assigned To],"*" & $B13,Table1[Status],"Archive") - COUNTIFS(Table1[Assigned To],$B13 & ",*",Table1[Status],"Archive") - COUNTIFS(Table1[Assigned To],"*" & $B13,Table1[Status],"Done") - COUNTIFS(Table1[Assigned To],$B13 & ",*",Table1[Status],"Done") -> 0 | D13: =COUNTIFS(Table1[Assigned To],"*" & $B13,Table1[Priority],"1") + COUNTIFS(Table1[Assigned To],$B13 & ",*",Table1[Priority],"1") - COUNTIFS(Table1[Assigned To],"*" & $B13,Table1[Status],"Archive",Table1[Priority],"1") - COUNTIFS(Table1[Assigned To],$B13 & ",*",Table1[Status],"Archive",Table1[Priority],"1") - COUNTIFS(Table1[Assigned To],"*" & $B13,Table1[Status],"Done",Table1[Priority],"1") - COUNTIFS(Table1[Assigned To],$B13 & ",*",Table1[Status],"Done",Table1[Priority],"1") -> 0 | E13: =IF(C13=0,0,D13/C13) -> 0 | F13: =COUNTIFS(Table1[Assigned To],"*" & $B13,Table1[Priority],"2") + COUNTIFS(Table1[Assigned To],$B13 & ",*",Table1[Priority],"2") - COUNTIFS(Table1[Assigned To],"*" & $B13,Table1[Status],"Archive",Table1[Priority],"2") - COUNTIFS(Table1[Assigned To],$B13 & ",*",Table1[Status],"Archive",Table1[Priority],"2") - COUNTIFS(Table1[Assigned To],"*" & $B13,Table1[Status],"Done",Table1[Priority],"2") - COUNTIFS(Table1[Assigned To],$B13 & ",*",Table1[Status],"Done",Table1[Priority],"2") -> 0 | G13: =IF(C13=0,0,F13/C13) -> 0 | H13: =COUNTIFS(Table1[Assigned To],"*" & $B13,Table1[Priority],"3") + COUNTIFS(Table1[Assigned To],$B13 & ",*",Table1[Priority],"3") - COUNTIFS(Table1[Assigned To],"*" & $B13,Table1[Status],"Archive",Table1[Priority],"3") - COUNTIFS(Table1[Assigned To],$B13 & ",*",Table1[Status],"Archive",Table1[Priority],"3") - COUNTIFS(Table1[Assigned To],"*" & $B13,Table1[Status],"Done",Table1[Priority],"3") - COUNTIFS(Table1[Assigned To],$B13 & ",*",Table1[Status],"Done",Table1[Priority],"3") -> 0 | I13: =IF(C13=0,0,H13/C13) -> 0 | J13: =COUNTIFS(Table1[Assigned To],"*" & $B13,Table1[Priority],"4") + COUNTIFS(Table1[Assigned To],$B13 & ",*",Table1[Priority],"4") - COUNTIFS(Table1[Assigned To],"*" & $B13,Table1[Status],"Archive",Table1[Priority],"4") - COUNTIFS(Table1[Assigned To],$B13 & ",*",Table1[Status],"Archive",Table1[Priority],"4") - COUNTIFS(Table1[Assigned To],"*" & $B13,Table1[Status],"Done",Table1[Priority],"4") - COUNTIFS(Table1[Assigned To],$B13 & ",*",Table1[Status],"Done",Table1[Priority],"4") -> 0 | K13: =IF(C13=0,0,J13/C13) -> 0 | L13: PB | M13: =IF(AND((D13/$C13)>D$2+0.05,$C13>4),2,IF(AND((D13/$C13)>D$2,$C13>4),1,0)) -> #DIV/0! | N13: =IF(AND((F13/$C13)>F$2+0.05,$C13>4),2,IF(AND((F13/$C13)>F$2,$C13>4),1,0)) -> #DIV/0! | O13: =IF(AND((H13/$C13)>H$2+0.05,$C13>4),2,IF(AND((H13/$C13)>H$2,$C13>4),1,0)) -> #DIV/0! | P13: =IF(AND((J13/$C13)>J$2,$C13>4),1,0) -> #DIV/0! | Q13: =SUM(D13,F13,H13,J13) -> 0
B14: Unassigned | C14: =COUNTIF(Table1[Assigned To],"*" & $B14) + COUNTIF(Table1[Assigned To],$B14 & ",*") - COUNTIFS(Table1[Assigned To],"*" & $B14,Table1[Status],"Archive") - COUNTIFS(Table1[Assigned To],$B14 & ",*",Table1[Status],"Archive") - COUNTIFS(Table1[Assigned To],"*" & $B14,Table1[Status],"Done") - COUNTIFS(Table1[Assigned To],$B14 & ",*",Table1[Status],"Done") -> 0 | D14: =COUNTIFS(Table1[Assigned To],"*" & $B14,Table1[Priority],"1") + COUNTIFS(Table1[Assigned To],$B14 & ",*",Table1[Priority],"1") - COUNTIFS(Table1[Assigned To],"*" & $B14,Table1[Status],"Archive",Table1[Priority],"1") - COUNTIFS(Table1[Assigned To],$B14 & ",*",Table1[Status],"Archive",Table1[Priority],"1") - COUNTIFS(Table1[Assigned To],"*" & $B14,Table1[Status],"Done",Table1[Priority],"1") - COUNTIFS(Table1[Assigned To],$B14 & ",*",Table1[Status],"Done",Table1[Priority],"1") -> 0 | E14: =IF(C14=0,0,D14/C14) -> 0 | F14: =COUNTIFS(Table1[Assigned To],"*" & $B14,Table1[Priority],"2") + COUNTIFS(Table1[Assigned To],$B14 & ",*",Table1[Priority],"2") - COUNTIFS(Table1[Assigned To],"*" & $B14,Table1[Status],"Archive",Table1[Priority],"2") - COUNTIFS(Table1[Assigned To],$B14 & ",*",Table1[Status],"Archive",Table1[Priority],"2") - COUNTIFS(Table1[Assigned To],"*" & $B14,Table1[Status],"Done",Table1[Priority],"2") - COUNTIFS(Table1[Assigned To],$B14 & ",*",Table1[Status],"Done",Table1[Priority],"2") -> 0 | G14: =IF(C14=0,0,F14/C14) -> 0 | H14: =COUNTIFS(Table1[Assigned To],"*" & $B14,Table1[Priority],"3") + COUNTIFS(Table1[Assigned To],$B14 & ",*",Table1[Priority],"3") - COUNTIFS(Table1[Assigned To],"*" & $B14,Table1[Status],"Archive",Table1[Priority],"3") - COUNTIFS(Table1[Assigned To],$B14 & ",*",Table1[Status],"Archive",Table1[Priority],"3") - COUNTIFS(Table1[Assigned To],"*" & $B14,Table1[Status],"Done",Table1[Priority],"3") - COUNTIFS(Table1[Assigned To],$B14 & ",*",Table1[Status],"Done",Table1[Priority],"3") -> 0 | I14: =IF(C14=0,0,H14/C14) -> 0 | J14: =COUNTIFS(Table1[Assigned To],"*" & $B14,Table1[Priority],"4") + COUNTIFS(Table1[Assigned To],$B14 & ",*",Table1[Priority],"4") - COUNTIFS(Table1[Assigned To],"*" & $B14,Table1[Status],"Archive",Table1[Priority],"4") - COUNTIFS(Table1[Assigned To],$B14 & ",*",Table1[Status],"Archive",Table1[Priority],"4") - COUNTIFS(Table1[Assigned To],"*" & $B14,Table1[Status],"Done",Table1[Priority],"4") - COUNTIFS(Table1[Assigned To],$B14 & ",*",Table1[Status],"Done",Table1[Priority],"4") -> 0 | K14: =IF(C14=0,0,J14/C14) -> 0 | L14: Notes | Q14: =SUM(D14,F14,H14,J14) -> 0
B15: David | C15: =COUNTIF(Table1[Assigned To],"*" & $B15) + COUNTIF(Table1[Assigned To],$B15 & ",*") - COUNTIFS(Table1[Assigned To],"*" & $B15,Table1[Status],"Archive") - COUNTIFS(Table1[Assigned To],$B15 & ",*",Table1[Status],"Archive") - COUNTIFS(Table1[Assigned To],"*" & $B15,Table1[Status],"Done") - COUNTIFS(Table1[Assigned To],$B15 & ",*",Table1[Status],"Done") -> 0 | D15: =COUNTIFS(Table1[Assigned To],"*" & $B15,Table1[Priority],"1") + COUNTIFS(Table1[Assigned To],$B15 & ",*",Table1[Priority],"1") - COUNTIFS(Table1[Assigned To],"*" & $B15,Table1[Status],"Archive",Table1[Priority],"1") - COUNTIFS(Table1[Assigned To],$B15 & ",*",Table1[Status],"Archive",Table1[Priority],"1") - COUNTIFS(Table1[Assigned To],"*" & $B15,Table1[Status],"Done",Table1[Priority],"1") - COUNTIFS(Table1[Assigned To],$B15 & ",*",Table1[Status],"Done",Table1[Priority],"1") -> 0 | E15: =IF(C15=0,0,D15/C15) -> 0 | F15: =COUNTIFS(Table1[Assigned To],"*" & $B15,Table1[Priority],"2") + COUNTIFS(Table1[Assigned To],$B15 & ",*",Table1[Priority],"2") - COUNTIFS(Table1[Assigned To],"*" & $B15,Table1[Status],"Archive",Table1[Priority],"2") - COUNTIFS(Table1[Assigned To],$B15 & ",*",Table1[Status],"Archive",Table1[Priority],"2") - COUNTIFS(Table1[Assigned To],"*" & $B15,Table1[Status],"Done",Table1[Priority],"2") - COUNTIFS(Table1[Assigned To],$B15 & ",*",Table1[Status],"Done",Table1[Priority],"2") -> 0 | G15: =IF(C15=0,0,F15/C15) -> 0 | H15: =COUNTIFS(Table1[Assigned To],"*" & $B15,Table1[Priority],"3") + COUNTIFS(Table1[Assigned To],$B15 & ",*",Table1[Priority],"3") - COUNTIFS(Table1[Assigned To],"*" & $B15,Table1[Status],"Archive",Table1[Priority],"3") - COUNTIFS(Table1[Assigned To],$B15 & ",*",Table1[Status],"Archive",Table1[Priority],"3") - COUNTIFS(Table1[Assigned To],"*" & $B15,Table1[Status],"Done",Table1[Priority],"3") - COUNTIFS(Table1[Assigned To],$B15 & ",*",Table1[Status],"Done",Table1[Priority],"3") -> 0 | I15: =IF(C15=0,0,H15/C15) -> 0 | J15: =COUNTIFS(Table1[Assigned To],"*" & $B15,Table1[Priority],"4") + COUNTIFS(Table1[Assigned To],$B15 & ",*",Table1[Priority],"4") - COUNTIFS(Table1[Assigned To],"*" & $B15,Table1[Status],"Archive",Table1[Priority],"4") - COUNTIFS(Table1[Assigned To],$B15 & ",*",Table1[Status],"Archive",Table1[Priority],"4") - COUNTIFS(Table1[Assigned To],"*" & $B15,Table1[Status],"Done",Table1[Priority],"4") - COUNTIFS(Table1[Assigned To],$B15 & ",*",Table1[Status],"Done",Table1[Priority],"4") -> 0 | K15: =IF(C15=0,0,J15/C15) -> 0 | L15: Ben | Q15: 0
B16: Sean | C16: =COUNTIF(Table1[Assigned To],"*" & $B16) + COUNTIF(Table1[Assigned To],$B16 & ",*") - COUNTIFS(Table1[Assigned To],"*" & $B16,Table1[Status],"Archive") - COUNTIFS(Table1[Assigned To],$B16 & ",*",Table1[Status],"Archive") - COUNTIFS(Table1[Assigned To],"*" & $B16,Table1[Status],"Done") - COUNTIFS(Table1[Assigned To],$B16 & ",*",Table1[Status],"Done") -> 0 | D16: =COUNTIFS(Table1[Assigned To],"*" & $B16,Table1[Priority],"1") + COUNTIFS(Table1[Assigned To],$B16 & ",*",Table1[Priority],"1") - COUNTIFS(Table1[Assigned To],"*" & $B16,Table1[Status],"Archive",Table1[Priority],"1") - COUNTIFS(Table1[Assigned To],$B16 & ",*",Table1[Status],"Archive",Table1[Priority],"1") - COUNTIFS(Table1[Assigned To],"*" & $B16,Table1[Status],"Done",Table1[Priority],"1") - COUNTIFS(Table1[Assigned To],$B16 & ",*",Table1[Status],"Done",Table1[Priority],"1") -> 0 | E16: =IF(C16=0,0,D16/C16) -> 0 | F16: =COUNTIFS(Table1[Assigned To],"*" & $B16,Table1[Priority],"2") + COUNTIFS(Table1[Assigned To],$B16 & ",*",Table1[Priority],"2") - COUNTIFS(Table1[Assigned To],"*" & $B16,Table1[Status],"Archive",Table1[Priority],"2") - COUNTIFS(Table1[Assigned To],$B16 & ",*",Table1[Status],"Archive",Table1[Priority],"2") - COUNTIFS(Table1[Assigned To],"*" & $B16,Table1[Status],"Done",Table1[Priority],"2") - COUNTIFS(Table1[Assigned To],$B16 & ",*",Table1[Status],"Done",Table1[Priority],"2") -> 0 | G16: =IF(C16=0,0,F16/C16) -> 0 | H16: =COUNTIFS(Table1[Assigned To],"*" & $B16,Table1[Priority],"3") + COUNTIFS(Table1[Assigned To],$B16 & ",*",Table1[Priority],"3") - COUNTIFS(Table1[Assigned To],"*" & $B16,Table1[Status],"Archive",Table1[Priority],"3") - COUNTIFS(Table1[Assigned To],$B16 & ",*",Table1[Status],"Archive",Table1[Priority],"3") - COUNTIFS(Table1[Assigned To],"*" & $B16,Table1[Status],"Done",Table1[Priority],"3") - COUNTIFS(Table1[Assigned To],$B16 & ",*",Table1[Status],"Done",Table1[Priority],"3") -> 0 | I16: =IF(C16=0,0,H16/C16) -> 0 | J16: =COUNTIFS(Table1[Assigned To],"*" & $B16,Table1[Priority],"4") + COUNTIFS(Table1[Assigned To],$B16 & ",*",Table1[Priority],"4") - COUNTIFS(Table1[Assigned To],"*" & $B16,Table1[Status],"Archive",Table1[Priority],"4") - COUNTIFS(Table1[Assigned To],$B16 & ",*",Table1[Status],"Archive",Table1[Priority],"4") - COUNTIFS(Table1[Assigned To],"*" & $B16,Table1[Status],"Done",Table1[Priority],"4") - COUNTIFS(Table1[Assigned To],$B16 & ",*",Table1[Status],"Done",Table1[Priority],"4") -> 0 | K16: =IF(C16=0,0,J16/C16) -> 0 | L16: Jon, Jacob | Q16: =SUM(D16,F16,H16,J16) -> 0
B17: Rick | C17: =COUNTIF(Table1[Assigned To],"*" & $B17) + COUNTIF(Table1[Assigned To],$B17 & ",*") - COUNTIFS(Table1[Assigned To],"*" & $B17,Table1[Status],"Archive") - COUNTIFS(Table1[Assigned To],$B17 & ",*",Table1[Status],"Archive") - COUNTIFS(Table1[Assigned To],"*" & $B17,Table1[Status],"Done") - COUNTIFS(Table1[Assigned To],$B17 & ",*",Table1[Status],"Done") -> 0 | D17: =COUNTIFS(Table1[Assigned To],"*" & $B17,Table1[Priority],"1") + COUNTIFS(Table1[Assigned To],$B17 & ",*",Table1[Priority],"1") - COUNTIFS(Table1[Assigned To],"*" & $B17,Table1[Status],"Archive",Table1[Priority],"1") - COUNTIFS(Table1[Assigned To],$B17 & ",*",Table1[Status],"Archive",Table1[Priority],"1") - COUNTIFS(Table1[Assigned To],"*" & $B17,Table1[Status],"Done",Table1[Priority],"1") - COUNTIFS(Table1[Assigned To],$B17 & ",*",Table1[Status],"Done",Table1[Priority],"1") -> 0 | E17: =IF(C17=0,0,D17/C17) -> 0 | F17: =COUNTIFS(Table1[Assigned To],"*" & $B17,Table1[Priority],"2") + COUNTIFS(Table1[Assigned To],$B17 & ",*",Table1[Priority],"2") - COUNTIFS(Table1[Assigned To],"*" & $B17,Table1[Status],"Archive",Table1[Priority],"2") - COUNTIFS(Table1[Assigned To],$B17 & ",*",Table1[Status],"Archive",Table1[Priority],"2") - COUNTIFS(Table1[Assigned To],"*" & $B17,Table1[Status],"Done",Table1[Priority],"2") - COUNTIFS(Table1[Assigned To],$B17 & ",*",Table1[Status],"Done",Table1[Priority],"2") -> 0 | G17: =IF(C17=0,0,F17/C17) -> 0 | H17: =COUNTIFS(Table1[Assigned To],"*" & $B17,Table1[Priority],"3") + COUNTIFS(Table1[Assigned To],$B17 & ",*",Table1[Priority],"3") - COUNTIFS(Table1[Assigned To],"*" & $B17,Table1[Status],"Archive",Table1[Priority],"3") - COUNTIFS(Table1[Assigned To],$B17 & ",*",Table1[Status],"Archive",Table1[Priority],"3") - COUNTIFS(Table1[Assigned To],"*" & $B17,Table1[Status],"Done",Table1[Priority],"3") - COUNTIFS(Table1[Assigned To],$B17 & ",*",Table1[Status],"Done",Table1[Priority],"3") -> 0 | I17: =IF(C17=0,0,H17/C17) -> 0 | J17: =COUNTIFS(Table1[Assigned To],"*" & $B17,Table1[Priority],"4") + COUNTIFS(Table1[Assigned To],$B17 & ",*",Table1[Priority],"4") - COUNTIFS(Table1[Assigned To],"*" & $B17,Table1[Status],"Archive",Table1[Priority],"4") - COUNTIFS(Table1[Assigned To],$B17 & ",*",Table1[Status],"Archive",Table1[Priority],"4") - COUNTIFS(Table1[Assigned To],"*" & $B17,Table1[Status],"Done",Table1[Priority],"4") - COUNTIFS(Table1[Assigned To],$B17 & ",*",Table1[Status],"Done",Table1[Priority],"4") -> 0 | K17: =IF(C17=0,0,J17/C17) -> 0 | L17: Jon, Nick | Q17: =SUM(D17,F17,H17,J17) -> 0
B18: Welder | C18: =COUNTIF(Table1[Assigned To],"*" & $B18) + COUNTIF(Table1[Assigned To],$B18 & ",*") - COUNTIFS(Table1[Assigned To],"*" & $B18,Table1[Status],"Archive") - COUNTIFS(Table1[Assigned To],$B18 & ",*",Table1[Status],"Archive") - COUNTIFS(Table1[Assigned To],"*" & $B18,Table1[Status],"Done") - COUNTIFS(Table1[Assigned To],$B18 & ",*",Table1[Status],"Done") -> 0 | D18: =COUNTIFS(Table1[Assigned To],"*" & $B18,Table1[Priority],"1") + COUNTIFS(Table1[Assigned To],$B18 & ",*",Table1[Priority],"1") - COUNTIFS(Table1[Assigned To],"*" & $B18,Table1[Status],"Archive",Table1[Priority],"1") - COUNTIFS(Table1[Assigned To],$B18 & ",*",Table1[Status],"Archive",Table1[Priority],"1") - COUNTIFS(Table1[Assigned To],"*" & $B18,Table1[Status],"Done",Table1[Priority],"1") - COUNTIFS(Table1[Assigned To],$B18 & ",*",Table1[Status],"Done",Table1[Priority],"1") -> 0 | E18: =IF(C18=0,0,D18/C18) -> 0 | F18: =COUNTIFS(Table1[Assigned To],"*" & $B18,Table1[Priority],"2") + COUNTIFS(Table1[Assigned To],$B18 & ",*",Table1[Priority],"2") - COUNTIFS(Table1[Assigned To],"*" & $B18,Table1[Status],"Archive",Table1[Priority],"2") - COUNTIFS(Table1[Assigned To],$B18 & ",*",Table1[Status],"Archive",Table1[Priority],"2") - COUNTIFS(Table1[Assigned To],"*" & $B18,Table1[Status],"Done",Table1[Priority],"2") - COUNTIFS(Table1[Assigned To],$B18 & ",*",Table1[Status],"Done",Table1[Priority],"2") -> 0 | G18: =IF(C18=0,0,F18/C18) -> 0 | H18: =COUNTIFS(Table1[Assigned To],"*" & $B18,Table1[Priority],"3") + COUNTIFS(Table1[Assigned To],$B18 & ",*",Table1[Priority],"3") - COUNTIFS(Table1[Assigned To],"*" & $B18,Table1[Status],"Archive",Table1[Priority],"3") - COUNTIFS(Table1[Assigned To],$B18 & ",*",Table1[Status],"Archive",Table1[Priority],"3") - COUNTIFS(Table1[Assigned To],"*" & $B18,Table1[Status],"Done",Table1[Priority],"3") - COUNTIFS(Table1[Assigned To],$B18 & ",*",Table1[Status],"Done",Table1[Priority],"3") -> 0 | I18: =IF(C18=0,0,H18/C18) -> 0 | J18: =COUNTIFS(Table1[Assigned To],"*" & $B18,Table1[Priority],"4") + COUNTIFS(Table1[Assigned To],$B18 & ",*",Table1[Priority],"4") - COUNTIFS(Table1[Assigned To],"*" & $B18,Table1[Status],"Archive",Table1[Priority],"4") - COUNTIFS(Table1[Assigned To],$B18 & ",*",Table1[Status],"Archive",Table1[Priority],"4") - COUNTIFS(Table1[Assigned To],"*" & $B18,Table1[Status],"Done",Table1[Priority],"4") - COUNTIFS(Table1[Assigned To],$B18 & ",*",Table1[Status],"Done",Table1[Priority],"4") -> 0 | K18: =IF(C18=0,0,J18/C18) -> 0 | L18: Ricky | Q18: =SUM(D18,F18,H18,J18) -> 0
B19: Christina | C19: =COUNTIF(Table1[Assigned To],"*" & $B19) + COUNTIF(Table1[Assigned To],$B19 & ",*") - COUNTIFS(Table1[Assigned To],"*" & $B19,Table1[Status],"Archive") - COUNTIFS(Table1[Assigned To],$B19 & ",*",Table1[Status],"Archive") - COUNTIFS(Table1[Assigned To],"*" & $B19,Table1[Status],"Done") - COUNTIFS(Table1[Assigned To],$B19 & ",*",Table1[Status],"Done") -> 0 | D19: =COUNTIFS(Table1[Assigned To],"*" & $B19,Table1[Priority],"1") + COUNTIFS(Table1[Assigned To],$B19 & ",*",Table1[Priority],"1") - COUNTIFS(Table1[Assigned To],"*" & $B19,Table1[Status],"Archive",Table1[Priority],"1") - COUNTIFS(Table1[Assigned To],$B19 & ",*",Table1[Status],"Archive",Table1[Priority],"1") - COUNTIFS(Table1[Assigned To],"*" & $B19,Table1[Status],"Done",Table1[Priority],"1") - COUNTIFS(Table1[Assigned To],$B19 & ",*",Table1[Status],"Done",Table1[Priority],"1") -> 0 | E19: =IF(C19=0,0,D19/C19) -> 0 | F19: =COUNTIFS(Table1[Assigned To],"*" & $B19,Table1[Priority],"2") + COUNTIFS(Table1[Assigned To],$B19 & ",*",Table1[Priority],"2") - COUNTIFS(Table1[Assigned To],"*" & $B19,Table1[Status],"Archive",Table1[Priority],"2") - COUNTIFS(Table1[Assigned To],$B19 & ",*",Table1[Status],"Archive",Table1[Priority],"2") - COUNTIFS(Table1[Assigned To],"*" & $B19,Table1[Status],"Done",Table1[Priority],"2") - COUNTIFS(Table1[Assigned To],$B19 & ",*",Table1[Status],"Done",Table1[Priority],"2") -> 0 | G19: =IF(C19=0,0,F19/C19) -> 0 | H19: =COUNTIFS(Table1[Assigned To],"*" & $B19,Table1[Priority],"3") + COUNTIFS(Table1[Assigned To],$B19 & ",*",Table1[Priority],"3") - COUNTIFS(Table1[Assigned To],"*" & $B19,Table1[Status],"Archive",Table1[Priority],"3") - COUNTIFS(Table1[Assigned To],$B19 & ",*",Table1[Status],"Archive",Table1[Priority],"3") - COUNTIFS(Table1[Assigned To],"*" & $B19,Table1[Status],"Done",Table1[Priority],"3") - COUNTIFS(Table1[Assigned To],$B19 & ",*",Table1[Status],"Done",Table1[Priority],"3") -> 0 | I19: =IF(C19=0,0,H19/C19) -> 0 | J19: =COUNTIFS(Table1[Assigned To],"*" & $B19,Table1[Priority],"4") + COUNTIFS(Table1[Assigned To],$B19 & ",*",Table1[Priority],"4") - COUNTIFS(Table1[Assigned To],"*" & $B19,Table1[Status],"Archive",Table1[Priority],"4") - COUNTIFS(Table1[Assigned To],$B19 & ",*",Table1[Status],"Archive",Table1[Priority],"4") - COUNTIFS(Table1[Assigned To],"*" & $B19,Table1[Status],"Done",Table1[Priority],"4") - COUNTIFS(Table1[Assigned To],$B19 & ",*",Table1[Status],"Done",Table1[Priority],"4") -> 0 | K19: =IF(C19=0,0,J19/C19) -> 0 | L19: Mike, Ken | Q19: =SUM(D19,F19,H19,J19) -> 0
B20: Ken | C20: =COUNTIF(Table1[Assigned To],"*" & $B20) + COUNTIF(Table1[Assigned To],$B20 & ",*") - COUNTIFS(Table1[Assigned To],"*" & $B20,Table1[Status],"Archive") - COUNTIFS(Table1[Assigned To],$B20 & ",*",Table1[Status],"Archive") - COUNTIFS(Table1[Assigned To],"*" & $B20,Table1[Status],"Done") - COUNTIFS(Table1[Assigned To],$B20 & ",*",Table1[Status],"Done") -> 0 | D20: =COUNTIFS(Table1[Assigned To],"*" & $B20,Table1[Priority],"1") + COUNTIFS(Table1[Assigned To],$B20 & ",*",Table1[Priority],"1") - COUNTIFS(Table1[Assigned To],"*" & $B20,Table1[Status],"Archive",Table1[Priority],"1") - COUNTIFS(Table1[Assigned To],$B20 & ",*",Table1[Status],"Archive",Table1[Priority],"1") - COUNTIFS(Table1[Assigned To],"*" & $B20,Table1[Status],"Done",Table1[Priority],"1") - COUNTIFS(Table1[Assigned To],$B20 & ",*",Table1[Status],"Done",Table1[Priority],"1") -> 0 | E20: =IF(C20=0,0,D20/C20) -> 0 | F20: =COUNTIFS(Table1[Assigned To],"*" & $B20,Table1[Priority],"2") + COUNTIFS(Table1[Assigned To],$B20 & ",*",Table1[Priority],"2") - COUNTIFS(Table1[Assigned To],"*" & $B20,Table1[Status],"Archive",Table1[Priority],"2") - COUNTIFS(Table1[Assigned To],$B20 & ",*",Table1[Status],"Archive",Table1[Priority],"2") - COUNTIFS(Table1[Assigned To],"*" & $B20,Table1[Status],"Done",Table1[Priority],"2") - COUNTIFS(Table1[Assigned To],$B20 & ",*",Table1[Status],"Done",Table1[Priority],"2") -> 0 | G20: =IF(C20=0,0,F20/C20) -> 0 | H20: =COUNTIFS(Table1[Assigned To],"*" & $B20,Table1[Priority],"3") + COUNTIFS(Table1[Assigned To],$B20 & ",*",Table1[Priority],"3") - COUNTIFS(Table1[Assigned To],"*" & $B20,Table1[Status],"Archive",Table1[Priority],"3") - COUNTIFS(Table1[Assigned To],$B20 & ",*",Table1[Status],"Archive",Table1[Priority],"3") - COUNTIFS(Table1[Assigned To],"*" & $B20,Table1[Status],"Done",Table1[Priority],"3") - COUNTIFS(Table1[Assigned To],$B20 & ",*",Table1[Status],"Done",Table1[Priority],"3") -> 0 | I20: =IF(C20=0,0,H20/C20) -> 0 | J20: =COUNTIFS(Table1[Assigned To],"*" & $B20,Table1[Priority],"4") + COUNTIFS(Table1[Assigned To],$B20 & ",*",Table1[Priority],"4") - COUNTIFS(Table1[Assigned To],"*" & $B20,Table1[Status],"Archive",Table1[Priority],"4") - COUNTIFS(Table1[Assigned To],$B20 & ",*",Table1[Status],"Archive",Table1[Priority],"4") - COUNTIFS(Table1[Assigned To],"*" & $B20,Table1[Status],"Done",Table1[Priority],"4") - COUNTIFS(Table1[Assigned To],$B20 & ",*",Table1[Status],"Done",Table1[Priority],"4") -> 0 | K20: =IF(C20=0,0,J20/C20) -> 0 | L20: Jacob | Q20: =SUM(D20,F20,H20,J20) -> 0
B21: #VALUE! | C21: =COUNTIF(Table1[Assigned To],"*" & $B21) + COUNTIF(Table1[Assigned To],$B21 & ",*") - COUNTIFS(Table1[Assigned To],"*" & $B21,Table1[Status],"Archive") - COUNTIFS(Table1[Assigned To],$B21 & ",*",Table1[Status],"Archive") - COUNTIFS(Table1[Assigned To],"*" & $B21,Table1[Status],"Done") - COUNTIFS(Table1[Assigned To],$B21 & ",*",Table1[Status],"Done") -> 0 | D21: =COUNTIFS(Table1[Assigned To],"*" & $B21,Table1[Priority],"1") + COUNTIFS(Table1[Assigned To],$B21 & ",*",Table1[Priority],"1") - COUNTIFS(Table1[Assigned To],"*" & $B21,Table1[Status],"Archive",Table1[Priority],"1") - COUNTIFS(Table1[Assigned To],$B21 & ",*",Table1[Status],"Archive",Table1[Priority],"1") - COUNTIFS(Table1[Assigned To],"*" & $B21,Table1[Status],"Done",Table1[Priority],"1") - COUNTIFS(Table1[Assigned To],$B21 & ",*",Table1[Status],"Done",Table1[Priority],"1") -> 0 | E21: =IF(C21=0,0,D21/C21) -> 0 | F21: =COUNTIFS(Table1[Assigned To],"*" & $B21,Table1[Priority],"2") + COUNTIFS(Table1[Assigned To],$B21 & ",*",Table1[Priority],"2") - COUNTIFS(Table1[Assigned To],"*" & $B21,Table1[Status],"Archive",Table1[Priority],"2") - COUNTIFS(Table1[Assigned To],$B21 & ",*",Table1[Status],"Archive",Table1[Priority],"2") - COUNTIFS(Table1[Assigned To],"*" & $B21,Table1[Status],"Done",Table1[Priority],"2") - COUNTIFS(Table1[Assigned To],$B21 & ",*",Table1[Status],"Done",Table1[Priority],"2") -> 0 | G21: =IF(C21=0,0,F21/C21) -> 0 | H21: =COUNTIFS(Table1[Assigned To],"*" & $B21,Table1[Priority],"3") + COUNTIFS(Table1[Assigned To],$B21 & ",*",Table1[Priority],"3") - COUNTIFS(Table1[Assigned To],"*" & $B21,Table1[Status],"Archive",Table1[Priority],"3") - COUNTIFS(Table1[Assigned To],$B21 & ",*",Table1[Status],"Archive",Table1[Priority],"3") - COUNTIFS(Table1[Assigned To],"*" & $B21,Table1[Status],"Done",Table1[Priority],"3") - COUNTIFS(Table1[Assigned To],$B21 & ",*",Table1[Status],"Done",Table1[Priority],"3") -> 0 | I21: =IF(C21=0,0,H21/C21) -> 0 | J21: =COUNTIFS(Table1[Assigned To],"*" & $B21,Table1[Priority],"4") + COUNTIFS(Table1[Assigned To],$B21 & ",*",Table1[Priority],"4") - COUNTIFS(Table1[Assigned To],"*" & $B21,Table1[Status],"Archive",Table1[Priority],"4") - COUNTIFS(Table1[Assigned To],$B21 & ",*",Table1[Status],"Archive",Table1[Priority],"4") - COUNTIFS(Table1[Assigned To],"*" & $B21,Table1[Status],"Done",Table1[Priority],"4") - COUNTIFS(Table1[Assigned To],$B21 & ",*",Table1[Status],"Done",Table1[Priority],"4") -> 0 | K21: =IF(C21=0,0,J21/C21) -> 0 | L21: Mike, Rick | Q21: =SUM(D21,F21,H21,J21) -> 0
B22: Kenny | C22: =COUNTIF(Table1[Assigned To],"*" & $B22) + COUNTIF(Table1[Assigned To],$B22 & ",*") - COUNTIFS(Table1[Assigned To],"*" & $B22,Table1[Status],"Archive") - COUNTIFS(Table1[Assigned To],$B22 & ",*",Table1[Status],"Archive") - COUNTIFS(Table1[Assigned To],"*" & $B22,Table1[Status],"Done") - COUNTIFS(Table1[Assigned To],$B22 & ",*",Table1[Status],"Done") -> 0 | D22: =COUNTIFS(Table1[Assigned To],"*" & $B22,Table1[Priority],"1") + COUNTIFS(Table1[Assigned To],$B22 & ",*",Table1[Priority],"1") - COUNTIFS(Table1[Assigned To],"*" & $B22,Table1[Status],"Archive",Table1[Priority],"1") - COUNTIFS(Table1[Assigned To],$B22 & ",*",Table1[Status],"Archive",Table1[Priority],"1") - COUNTIFS(Table1[Assigned To],"*" & $B22,Table1[Status],"Done",Table1[Priority],"1") - COUNTIFS(Table1[Assigned To],$B22 & ",*",Table1[Status],"Done",Table1[Priority],"1") -> 0 | E22: =IF(C22=0,0,D22/C22) -> 0 | F22: =COUNTIFS(Table1[Assigned To],"*" & $B22,Table1[Priority],"2") + COUNTIFS(Table1[Assigned To],$B22 & ",*",Table1[Priority],"2") - COUNTIFS(Table1[Assigned To],"*" & $B22,Table1[Status],"Archive",Table1[Priority],"2") - COUNTIFS(Table1[Assigned To],$B22 & ",*",Table1[Status],"Archive",Table1[Priority],"2") - COUNTIFS(Table1[Assigned To],"*" & $B22,Table1[Status],"Done",Table1[Priority],"2") - COUNTIFS(Table1[Assigned To],$B22 & ",*",Table1[Status],"Done",Table1[Priority],"2") -> 0 | G22: =IF(C22=0,0,F22/C22) -> 0 | H22: =COUNTIFS(Table1[Assigned To],"*" & $B22,Table1[Priority],"3") + COUNTIFS(Table1[Assigned To],$B22 & ",*",Table1[Priority],"3") - COUNTIFS(Table1[Assigned To],"*" & $B22,Table1[Status],"Archive",Table1[Priority],"3") - COUNTIFS(Table1[Assigned To],$B22 & ",*",Table1[Status],"Archive",Table1[Priority],"3") - COUNTIFS(Table1[Assigned To],"*" & $B22,Table1[Status],"Done",Table1[Priority],"3") - COUNTIFS(Table1[Assigned To],$B22 & ",*",Table1[Status],"Done",Table1[Priority],"3") -> 0 | I22: =IF(C22=0,0,H22/C22) -> 0 | J22: =COUNTIFS(Table1[Assigned To],"*" & $B22,Table1[Priority],"4") + COUNTIFS(Table1[Assigned To],$B22 & ",*",Table1[Priority],"4") - COUNTIFS(Table1[Assigned To],"*" & $B22,Table1[Status],"Archive",Table1[Priority],"4") - COUNTIFS(Table1[Assigned To],$B22 & ",*",Table1[Status],"Archive",Table1[Priority],"4") - COUNTIFS(Table1[Assigned To],"*" & $B22,Table1[Status],"Done",Table1[Priority],"4") - COUNTIFS(Table1[Assigned To],$B22 & ",*",Table1[Status],"Done",Table1[Priority],"4") -> 0 | K22: =IF(C22=0,0,J22/C22) -> 0 | L22: Jon, Brandon | Q22: =SUM(D22,F22,H22,J22) -> 0
B23: Eli | C23: =COUNTIF(Table1[Assigned To],"*" & $B23) + COUNTIF(Table1[Assigned To],$B23 & ",*") - COUNTIFS(Table1[Assigned To],"*" & $B23,Table1[Status],"Archive") - COUNTIFS(Table1[Assigned To],$B23 & ",*",Table1[Status],"Archive") - COUNTIFS(Table1[Assigned To],"*" & $B23,Table1[Status],"Done") - COUNTIFS(Table1[Assigned To],$B23 & ",*",Table1[Status],"Done") -> 0 | D23: =COUNTIFS(Table1[Assigned To],"*" & $B23,Table1[Priority],"1") + COUNTIFS(Table1[Assigned To],$B23 & ",*",Table1[Priority],"1") - COUNTIFS(Table1[Assigned To],"*" & $B23,Table1[Status],"Archive",Table1[Priority],"1") - COUNTIFS(Table1[Assigned To],$B23 & ",*",Table1[Status],"Archive",Table1[Priority],"1") - COUNTIFS(Table1[Assigned To],"*" & $B23,Table1[Status],"Done",Table1[Priority],"1") - COUNTIFS(Table1[Assigned To],$B23 & ",*",Table1[Status],"Done",Table1[Priority],"1") -> 0 | E23: =IF(C23=0,0,D23/C23) -> 0 | F23: =COUNTIFS(Table1[Assigned To],"*" & $B23,Table1[Priority],"2") + COUNTIFS(Table1[Assigned To],$B23 & ",*",Table1[Priority],"2") - COUNTIFS(Table1[Assigned To],"*" & $B23,Table1[Status],"Archive",Table1[Priority],"2") - COUNTIFS(Table1[Assigned To],$B23 & ",*",Table1[Status],"Archive",Table1[Priority],"2") - COUNTIFS(Table1[Assigned To],"*" & $B23,Table1[Status],"Done",Table1[Priority],"2") - COUNTIFS(Table1[Assigned To],$B23 & ",*",Table1[Status],"Done",Table1[Priority],"2") -> 0 | G23: =IF(C23=0,0,F23/C23) -> 0 | H23: =COUNTIFS(Table1[Assigned To],"*" & $B23,Table1[Priority],"3") + COUNTIFS(Table1[Assigned To],$B23 & ",*",Table1[Priority],"3") - COUNTIFS(Table1[Assigned To],"*" & $B23,Table1[Status],"Archive",Table1[Priority],"3") - COUNTIFS(Table1[Assigned To],$B23 & ",*",Table1[Status],"Archive",Table1[Priority],"3") - COUNTIFS(Table1[Assigned To],"*" & $B23,Table1[Status],"Done",Table1[Priority],"3") - COUNTIFS(Table1[Assigned To],$B23 & ",*",Table1[Status],"Done",Table1[Priority],"3") -> 0 | I23: =IF(C23=0,0,H23/C23) -> 0 | J23: =COUNTIFS(Table1[Assigned To],"*" & $B23,Table1[Priority],"4") + COUNTIFS(Table1[Assigned To],$B23 & ",*",Table1[Priority],"4") - COUNTIFS(Table1[Assigned To],"*" & $B23,Table1[Status],"Archive",Table1[Priority],"4") - COUNTIFS(Table1[Assigned To],$B23 & ",*",Table1[Status],"Archive",Table1[Priority],"4") - COUNTIFS(Table1[Assigned To],"*" & $B23,Table1[Status],"Done",Table1[Priority],"4") - COUNTIFS(Table1[Assigned To],$B23 & ",*",Table1[Status],"Done",Table1[Priority],"4") -> 0 | K23: =IF(C23=0,0,J23/C23) -> 0 | L23: Unassigned | Q23: =SUM(D23,F23,H23,J23) -> 0
B24: MAINT | L24: Jon, Sean
B25: Jason | L25: Tom, Mike, Jacob
L26: David
L27: Nick, Jon
L28: Jon, Nick, Mike
L29: Tom, Rick
L30: Ricky, Jon, Nick
L31: Sean
L32: Rick
L33: Tom, Jacob
L34: Nick, David
L35: Jon, Ricky, Sean
L36: Jon, Ricky
L37: Sean, RIcky
... L91: Jacob, Welder

Sheet Ebay Listing
A1: Ebay Link | B1: Ebay Number | C1: Description | D1: Quantity | E1: Status | F1: Location | G1: Invoice Number | H1: Item Notes
A2: =HYPERLINK("https://www.ebay.com/itm/" & B2, "eBay Listing") -> eBay Listing | B2: 132902137746 | C2: IFM AC2900 - AS-Interface ProcessLine module ProcessLine 8 SB IP69K | D2: 3 | E2: Open
A3: =HYPERLINK("https://www.ebay.com/itm/" & B3, "eBay Listing") -> eBay Listing | B3: 133002385666 | C3: Konecranes XN 5 1-ton Electric Chain Hoist with Trolley | D3: 2 | E3: Open
A4: =HYPERLINK("https://www.ebay.com/itm/" & B4, "eBay Listing") -> eBay Listing | B4: 133002385677 | C4: LMI metering pump model #A751-297 variable speed / stroke stainless head | D4: 1 | E4: Open
A5: =HYPERLINK("https://www.ebay.com/itm/" & B5, "eBay Listing") -> eBay Listing | B5: 133028684194 | C5: qty 10 Haas BT40 BT-40 Pull Studs retention knobs 40 taper M16 202-5923 cat | D5: 1 | E5: Open
A6: =HYPERLINK("https://www.ebay.com/itm/" & B6, "eBay Listing") -> eBay Listing | B6: 133028684197 | C6: FANUC Pulse Coder Encoder Alpha A64; Part No. A860-0360-V501 New | D6: 1 | E6: Open
A7: =HYPERLINK("https://www.ebay.com/itm/" & B7, "eBay Listing") -> eBay Listing | B7: 133028684204 | C7: Ampco ZP-3 130 Positive displacement 15 30 45 60 220 pump Sanitary Waukesha 130 | D7: 1 | E7: Open
A8: =HYPERLINK("https://www.ebay.com/itm/" & B8, "eBay Listing") -> eBay Listing | B8: 133104792032 | C8: Allen-Bradley 1756-L1/A M1/A (1756-L1) Processor/Controller PLC Control Logix | D8: 1 | E8: Open
A9: =HYPERLINK("https://www.ebay.com/itm/" & B9, "eBay Listing") -> eBay Listing | B9: 133393211198 | C9: Stainless Steel Dispenser Stand - Laser Engraved / Customizable | D9: 100 | E9: Open
A10: =HYPERLINK("https://www.ebay.com/itm/" & B10, "eBay Listing") -> eBay Listing | B10: 133572735535 | C10: APS sanitary Tubular Double Tube Stainless Heat Exchanger 10'x 2" maple syrup | D10: 2 | E10: Open
A11: =HYPERLINK("https://www.ebay.com/itm/" & B11, "eBay Listing") -> eBay Listing | B11: 133615871643 | C11: 60 GALLON STAINLESS STEEL DAIRY BALANCE TANK PMO Rosemount level sensor | D11: 1 | E11: Open
A12: =HYPERLINK("https://www.ebay.com/itm/" & B12, "eBay Listing") -> eBay Listing | B12: 133619611102 | C12: Reduced for quick Sale Commercial HAVECON GLASS VENLO Dutch GREENHOUSE 300K Sqft | D12: 1 | E12: Open
A13: =HYPERLINK("https://www.ebay.com/itm/" & B13, "eBay Listing") -> eBay Listing | B13: 133619921177 | C13: Mitsubishi FA20S Wire EDM (2011) 2100hrs on it. | D13: 1 | E13: Open
... A176: =HYPERLINK("https://www.ebay.com/itm/" & B176, "eBay Listing") -> eBay Listing | B176: 135835078951 | C176: Bitzer scroll compressor GSD80385VwB4-1 refrigeration R410a 460V 60Hz new | D176: 1 | E176: Open
A177: =HYPERLINK("https://www.ebay.com/itm/" & B177, "eBay Listing") -> eBay Listing
A178: =HYPERLINK("https://www.ebay.com/itm/" & B178, "eBay Listing") -> eBay Listing
A179: =HYPERLINK("https://www.ebay.com/itm/" & B179, "eBay Listing") -> eBay Listing
A180: =HYPERLINK("https://www.ebay.com/itm/" & B180, "eBay Listing") -> eBay Listing
A181: =HYPERLINK("https://www.ebay.com/itm/" & B181, "eBay Listing") -> eBay Listing
A182: =HYPERLINK("https://www.ebay.com/itm/" & B182, "eBay Listing") -> eBay Listing
A183: =HYPERLINK("https://www.ebay.com/itm/" & B183, "eBay Listing") -> eBay Listing
A184: =HYPERLINK("https://www.ebay.com/itm/" & B184, "eBay Listing") -> eBay Listing
A185: =HYPERLINK("https://www.ebay.com/itm/" & B185, "eBay Listing") -> eBay Listing
A186: =HYPERLINK("https://www.ebay.com/itm/" & B186, "eBay Listing") -> eBay Listing
A187: =HYPERLINK("https://www.ebay.com/itm/" & B187, "eBay Listing") -> eBay Listing
A188: =HYPERLINK("https://www.ebay.com/itm/" & B188, "eBay Listing") -> eBay Listing
... A199: =HYPERLINK("https://www.ebay.com/itm/" & B199, "eBay Listing") -> eBay Listing
